[
  {
    "content_id": 809912,
    "reference_id": 131029,
    "version": "1.0.1",
    "title": "फिलिप्पियों 1:1",
    "media_type": "Text",
    "index_reference": "50001001",
    "language": "hin",
    "review_level": "None",
    "content": "<p><strong>पौलुस ने यह पत्र किसे संबोधित किया है?</strong></p><p>पौलुस ने इस पत्र में उन सब पवित्र लोगों को जो मसीह यीशु में होकर  फिलिप्पी में रहते थे और साथ ही उनके <span>अध्यक्षों और सेवकों को संबोधित किया है</span>।</p>",
    "associations": {
      "passage": [
        {
          "start_ref": "50001001",
          "start_ref_usfm": "PHP 1:1",
          "end_ref": "50001001",
          "end_ref_usfm": "PHP 1:1"
        }
      ],
      "resource": []
    }
  },
  {
    "content_id": 809913,
    "reference_id": 131030,
    "version": "1.0.1",
    "title": "फिलिप्पियों 1:5",
    "media_type": "Text",
    "index_reference": "50001005",
    "language": "hin",
    "review_level": "None",
    "content": "<p><strong>पौलुस ने फिलिप्पियों के लिए परमेश्वर को किस बात के लिए धन्यवाद दिया?</strong></p><p>पौलुस ने पहले दिन से लेकर अब तक सुसमाचार <span>फैलाने</span> में फिलिप्पियों की सहभागिता के लिए परमेश्वर को धन्यवाद दिया।</p>",
    "associations": {
      "passage": [
        {
          "start_ref": "50001005",
          "start_ref_usfm": "PHP 1:5",
          "end_ref": "50001005",
          "end_ref_usfm": "PHP 1:5"
        }
      ],
      "resource": []
    }
  },
  {
    "content_id": 809914,
    "reference_id": 131031,
    "version": "1.0.1",
    "title": "फिलिप्पियों 1:6",
    "media_type": "Text",
    "index_reference": "50001006",
    "language": "hin",
    "review_level": "None",
    "content": "<p><strong>पौलुस को फिलिप्पियों के बारे में किस बात का भरोसा था?</strong></p><p>पौलुस को भरोसा था कि जिसने उनमें अच्छा कार्य आरंभ किया है, <span>वही उसे यीशु मसीह के दिन तक पूरा करेगा। </span></p>",
    "associations": {
      "passage": [
        {
          "start_ref": "50001006",
          "start_ref_usfm": "PHP 1:6",
          "end_ref": "50001006",
          "end_ref_usfm": "PHP 1:6"
        }
      ],
      "resource": []
    }
  },
  {
    "content_id": 809915,
    "reference_id": 131032,
    "version": "1.0.1",
    "title": "फिलिप्पियों 1:7",
    "media_type": "Text",
    "index_reference": "50001007",
    "language": "hin",
    "review_level": "None",
    "content": "<p><strong>फिलिप्पियों की कलीसिया किसमें पौलुस के सहभागी थे?</strong></p><p>फिलिप्पियों की कलीसिया पौलुस के <span>कैद में और सुसमाचार के लिये उत्तर और प्रमाण देने में उसके साथ अनुग्रह में सहभागी थे</span>।</p>",
    "associations": {
      "passage": [
        {
          "start_ref": "50001007",
          "start_ref_usfm": "PHP 1:7",
          "end_ref": "50001007",
          "end_ref_usfm": "PHP 1:7"
        }
      ],
      "resource": []
    }
  },
  {
    "content_id": 809916,
    "reference_id": 131033,
    "version": "1.0.1",
    "title": "फिलिप्पियों 1:9",
    "media_type": "Text",
    "index_reference": "50001009",
    "language": "hin",
    "review_level": "None",
    "content": "<p><strong>पौलुस ने फिलिप्पियों की कलीसिया में क्या बढ़ते जाने के लिए प्रार्थना करी?</strong></p><p>पौलुस ने प्रार्थना करी कि फिलिप्पियों की कलीसिया <span>प्रेम, ज्ञान और सब प्रकार के विवेक में और </span>अधिक बढ़ता जाए।</p>",
    "associations": {
      "passage": [
        {
          "start_ref": "50001009",
          "start_ref_usfm": "PHP 1:9",
          "end_ref": "50001009",
          "end_ref_usfm": "PHP 1:9"
        }
      ],
      "resource": []
    }
  },
  {
    "content_id": 809917,
    "reference_id": 131034,
    "version": "1.0.1",
    "title": "फिलिप्पियों 1:11",
    "media_type": "Text",
    "index_reference": "50001011",
    "language": "hin",
    "review_level": "None",
    "content": "<p><strong>पौलुस ने फिलिप्पियों की कलीसिया के लिए किस चीज से </strong><span><strong>भरपूर होते जाने की इच्छा की </strong></span><strong>?</strong></p><p>पौलुस चाहते थे कि फिलिप्पियों की कलीसिया <span>धार्मिकता के फलों से भरपूर होती जाए। </span></p>",
    "associations": {
      "passage": [
        {
          "start_ref": "50001011",
          "start_ref_usfm": "PHP 1:11",
          "end_ref": "50001011",
          "end_ref_usfm": "PHP 1:11"
        }
      ],
      "resource": []
    }
  },
  {
    "content_id": 809918,
    "reference_id": 131035,
    "version": "1.0.1",
    "title": "फिलिप्पियों 1:12–14",
    "media_type": "Text",
    "index_reference": "50001012-50001014",
    "language": "hin",
    "review_level": "None",
    "content": "<p><strong>पौलुस के कैद में होने से सुसमाचार की उन्नति कैसे हुई?</strong></p><p>मसीह के लिए पौलुस की कैद की बात सब जानते थे, और अब अधिकांश भाई और भी परमेश्वर का वचन बेधड़क सुना रहे थे।</p>",
    "associations": {
      "passage": [
        {
          "start_ref": "50001012",
          "start_ref_usfm": "PHP 1:12",
          "end_ref": "50001014",
          "end_ref_usfm": "PHP 1:14"
        }
      ],
      "resource": []
    }
  },
  {
    "content_id": 809919,
    "reference_id": 131036,
    "version": "1.0.1",
    "title": "फिलिप्पियों 1:17",
    "media_type": "Text",
    "index_reference": "50001017",
    "language": "hin",
    "review_level": "None",
    "content": "<p><span><strong>कई लोग सिधाई से नहीं पर विरोध से मसीह की कथा क्यों सुनाते थे </strong></span><strong>?</strong></p><p><span>कई लोग सिधाई से नहीं पर विरोध से मसीह की कथा, </span>यह सोचते हुए <span>सुनाते थे, कि कैद में </span>पौलुस के <span>लिये क्लेश उत्पन्न करें। </span></p><p></p>",
    "associations": {
      "passage": [
        {
          "start_ref": "50001017",
          "start_ref_usfm": "PHP 1:17",
          "end_ref": "50001017",
          "end_ref_usfm": "PHP 1:17"
        }
      ],
      "resource": []
    }
  },
  {
    "content_id": 809920,
    "reference_id": 131037,
    "version": "1.0.1",
    "title": "फिलिप्पियों 1:18",
    "media_type": "Text",
    "index_reference": "50001018",
    "language": "hin",
    "review_level": "None",
    "content": "<p><strong>मसीह के सच्चे और बहाने से की गई प्रचार के प्रति पौलुस की क्या प्रतिक्रिया थी?</strong></p><p>पौलुस इस बात से <span>आनन्दित</span> था कि किसी भी रीति से मसीह की कथा सुनाई जा रही थी।</p>",
    "associations": {
      "passage": [
        {
          "start_ref": "50001018",
          "start_ref_usfm": "PHP 1:18",
          "end_ref": "50001018",
          "end_ref_usfm": "PHP 1:18"
        }
      ],
      "resource": []
    }
  },
  {
    "content_id": 809921,
    "reference_id": 131038,
    "version": "1.0.1",
    "title": "फिलिप्पियों 1:20",
    "media_type": "Text",
    "index_reference": "50001020",
    "language": "hin",
    "review_level": "None",
    "content": "<p><strong>पौलुस अपने जीवित रहने में या मरने में क्या करना चाहते थे?</strong></p><p>पौलुस चाहते थे कि चाहे उनके जीवित रहने में या मरने में, वह मसीह की बड़ाई प्रगट करे।</p>",
    "associations": {
      "passage": [
        {
          "start_ref": "50001020",
          "start_ref_usfm": "PHP 1:20",
          "end_ref": "50001020",
          "end_ref_usfm": "PHP 1:20"
        }
      ],
      "resource": []
    }
  },
  {
    "content_id": 809922,
    "reference_id": 131039,
    "version": "1.0.1",
    "title": "फिलिप्पियों 1:21",
    "media_type": "Text",
    "index_reference": "50001021",
    "language": "hin",
    "review_level": "None",
    "content": "<p><strong>पौलुस </strong><span><strong>के लिये जीवित रहना, और मर जाना क्या है</strong></span><strong>?</strong></p><p>पौलुस के लिये <span>जीवित रहना मसीह है, और मर जाना लाभ है</span>।</p>",
    "associations": {
      "passage": [
        {
          "start_ref": "50001021",
          "start_ref_usfm": "PHP 1:21",
          "end_ref": "50001021",
          "end_ref_usfm": "PHP 1:21"
        }
      ],
      "resource": []
    }
  },
  {
    "content_id": 809923,
    "reference_id": 131040,
    "version": "1.0.1",
    "title": "फिलिप्पियों 1:22–24",
    "media_type": "Text",
    "index_reference": "50001022-50001024",
    "language": "hin",
    "review_level": "None",
    "content": "<p><strong>पौलुस किसके बीच </strong><span><strong>असमंजस में थे</strong></span><strong>?</strong></p><p>पौलुस दोनों के बीच असमंजस में थे कि वह <span>देह-त्याग कर मसीह के पास जा रहे या </span>फिर शरीर में रहकर अपना कार्य जारी रखे। <span> </span></p><p></p>",
    "associations": {
      "passage": [
        {
          "start_ref": "50001022",
          "start_ref_usfm": "PHP 1:22",
          "end_ref": "50001024",
          "end_ref_usfm": "PHP 1:24"
        }
      ],
      "resource": []
    }
  },
  {
    "content_id": 809924,
    "reference_id": 131041,
    "version": "1.0.1",
    "title": "फिलिप्पियों 1:25",
    "media_type": "Text",
    "index_reference": "50001025",
    "language": "hin",
    "review_level": "None",
    "content": "<p><strong>पौलुस को किस बात का भरोसा था कि वह फिलिप्पियों के साथ रहेंगे?</strong></p><p>पौलुस को पूरा भरोसा था कि वह फिलिप्पियों के विश्वास में <span>दृढ़ होते जाने</span> और आनन्द के लिए उनके साथ रहेंगे।</p>",
    "associations": {
      "passage": [
        {
          "start_ref": "50001025",
          "start_ref_usfm": "PHP 1:25",
          "end_ref": "50001025",
          "end_ref_usfm": "PHP 1:25"
        }
      ],
      "resource": []
    }
  },
  {
    "content_id": 809925,
    "reference_id": 131042,
    "version": "1.0.1",
    "title": "फिलिप्पियों 1:27",
    "media_type": "Text",
    "index_reference": "50001027",
    "language": "hin",
    "review_level": "None",
    "content": "<p><strong>चाहे फिलिप्पियों के साथ हो या उनसे दूर, पौलुस फिलिप्पियों के विषय में क्या सुनना चाहते थे?</strong></p><p>पौलुस यह सुनना चाहते थे कि फिलिप्पियों का <span>चाल-चलन मसीह के सुसमाचार के योग्य </span>हैं और वे <span>एक ही आत्मा में स्थिर हैं, और एक चित्त होकर सुसमाचार के विश्वास के लिये परिश्रम करते हैं। </span></p>",
    "associations": {
      "passage": [
        {
          "start_ref": "50001027",
          "start_ref_usfm": "PHP 1:27",
          "end_ref": "50001027",
          "end_ref_usfm": "PHP 1:27"
        }
      ],
      "resource": []
    }
  },
  {
    "content_id": 809926,
    "reference_id": 131043,
    "version": "1.0.1",
    "title": "फिलिप्पियों 1:28",
    "media_type": "Text",
    "index_reference": "50001028",
    "language": "hin",
    "review_level": "None",
    "content": "<p><strong>जब फिलिप्पी </strong><span><strong>के लोग किसी बात में विरोधियों से भय नहीं खाते तो यह उनके लिये किसका स्पष्ट चिन्ह था</strong></span><strong>?</strong></p><p>जब फिलिप्पी के लोग <span>किसी बात में विरोधियों से भय नहीं खाते </span>तो यह उनके विरोधियों के विनाश का स्पष्ट चिन्ह था, परन्तु विश्वासियों के उद्धार का, जो परमेश्वर की ओर से था।</p>",
    "associations": {
      "passage": [
        {
          "start_ref": "50001028",
          "start_ref_usfm": "PHP 1:28",
          "end_ref": "50001028",
          "end_ref_usfm": "PHP 1:28"
        }
      ],
      "resource": []
    }
  },
  {
    "content_id": 809927,
    "reference_id": 131044,
    "version": "1.0.1",
    "title": "फिलिप्पियों 1:29",
    "media_type": "Text",
    "index_reference": "50001029",
    "language": "hin",
    "review_level": "None",
    "content": "<p><strong>परमेश्‍वर ने फिलिप्पियों को कौन सी दो चीज़ें दी थीं?</strong></p><p>फिलिप्पियों को यह अनुग्रह दिया गया था कि वे मसीह पर विश्वास करें, परन्तु साथ ही यह भी कि वे उसके लिए दुःख भी उठाएं।</p>",
    "associations": {
      "passage": [
        {
          "start_ref": "50001029",
          "start_ref_usfm": "PHP 1:29",
          "end_ref": "50001029",
          "end_ref_usfm": "PHP 1:29"
        }
      ],
      "resource": []
    }
  },
  {
    "content_id": 809928,
    "reference_id": 131045,
    "version": "1.0.1",
    "title": "फिलिप्पियों 2:2",
    "media_type": "Text",
    "index_reference": "50002002",
    "language": "hin",
    "review_level": "None",
    "content": "<p><strong>पौलुस कहते हैं कि फिलिप्पी के लोग उनका </strong><span><strong>आनन्द </strong></span><strong>कैसे पूरा करें ?</strong></p><p>पौलुस कहते हैं कि फिलिप्पी के लोग <span>एक मन रहें और एक ही प्रेम, एक ही चित्त, और एक ही मनसा रखें ताकि उनका आनन्द पूरा हो। </span></p>",
    "associations": {
      "passage": [
        {
          "start_ref": "50002002",
          "start_ref_usfm": "PHP 2:2",
          "end_ref": "50002002",
          "end_ref_usfm": "PHP 2:2"
        }
      ],
      "resource": []
    }
  },
  {
    "content_id": 809929,
    "reference_id": 131046,
    "version": "1.0.1",
    "title": "फिलिप्पियों 2:3",
    "media_type": "Text",
    "index_reference": "50002003",
    "language": "hin",
    "review_level": "None",
    "content": "<p><strong>पौलुस कहते हैं कि फिलिप्पियों को एक-दूसरे को कैसे समझना  चाहिए?</strong></p><p>फिलिप्पियों को <span>दीनता से एक दूसरे को अपने से अच्छा समझना चाहिए</span>।</p>",
    "associations": {
      "passage": [
        {
          "start_ref": "50002003",
          "start_ref_usfm": "PHP 2:3",
          "end_ref": "50002003",
          "end_ref_usfm": "PHP 2:3"
        }
      ],
      "resource": []
    }
  },
  {
    "content_id": 809930,
    "reference_id": 131047,
    "version": "1.0.1",
    "title": "फिलिप्पियों 2:5–6",
    "media_type": "Text",
    "index_reference": "50002005-50002006",
    "language": "hin",
    "review_level": "None",
    "content": "<p><strong>पौलुस के अनुसार हमारा स्वभाव किसके जैसा होना चाहिए?</strong></p><p>पौलुस कहते हैं कि हमारा स्वभाव मसीह यीशु के जैसा होना चाहिए।</p>",
    "associations": {
      "passage": [
        {
          "start_ref": "50002005",
          "start_ref_usfm": "PHP 2:5",
          "end_ref": "50002006",
          "end_ref_usfm": "PHP 2:6"
        }
      ],
      "resource": []
    }
  },
  {
    "content_id": 809931,
    "reference_id": 131048,
    "version": "1.0.1",
    "title": "फिलिप्पियों 2:6",
    "media_type": "Text",
    "index_reference": "50002006",
    "language": "hin",
    "review_level": "None",
    "content": "<p><strong>मसीह यीशु किसके स्वरूप में विद्यमान हैं?</strong></p><p>मसीह यीशु परमेश्वर के स्वरूप में विद्यमान हैं।</p>",
    "associations": {
      "passage": [
        {
          "start_ref": "50002006",
          "start_ref_usfm": "PHP 2:6",
          "end_ref": "50002006",
          "end_ref_usfm": "PHP 2:6"
        }
      ],
      "resource": []
    }
  },
  {
    "content_id": 809932,
    "reference_id": 131049,
    "version": "1.0.1",
    "title": "फिलिप्पियों 2:7",
    "media_type": "Text",
    "index_reference": "50002007",
    "language": "hin",
    "review_level": "None",
    "content": "<p><strong>मसीह यीशु ने कौन सा स्वरूप धारण किया?</strong></p><p>मसीह यीशु ने एक दास का स्वरूप धारण किया और मनुष्य की समानता में हो गए। </p>",
    "associations": {
      "passage": [
        {
          "start_ref": "50002007",
          "start_ref_usfm": "PHP 2:7",
          "end_ref": "50002007",
          "end_ref_usfm": "PHP 2:7"
        }
      ],
      "resource": []
    }
  },
  {
    "content_id": 809933,
    "reference_id": 131050,
    "version": "1.0.1",
    "title": "फिलिप्पियों 2:8",
    "media_type": "Text",
    "index_reference": "50002008",
    "language": "hin",
    "review_level": "None",
    "content": "<p><strong>यीशु ने अपने आप को किस प्रकार दीन किया?</strong></p><p>यीशु ने क्रूस पर मृत्यु तक आज्ञाकारी रह कर अपने आप को दीन किया।</p>",
    "associations": {
      "passage": [
        {
          "start_ref": "50002008",
          "start_ref_usfm": "PHP 2:8",
          "end_ref": "50002008",
          "end_ref_usfm": "PHP 2:8"
        }
      ],
      "resource": []
    }
  },
  {
    "content_id": 809934,
    "reference_id": 131051,
    "version": "1.0.1",
    "title": "फिलिप्पियों 2:9",
    "media_type": "Text",
    "index_reference": "50002009",
    "language": "hin",
    "review_level": "None",
    "content": "<p><strong>फिर परमेश्वर ने यीशु के लिए क्या किया?</strong></p><p>परमेश्वर ने यीशु को अति महान किया और उन्हें वो नाम दिया जो सब नामों में श्रेष्ठ है।</p>",
    "associations": {
      "passage": [
        {
          "start_ref": "50002009",
          "start_ref_usfm": "PHP 2:9",
          "end_ref": "50002009",
          "end_ref_usfm": "PHP 2:9"
        }
      ],
      "resource": []
    }
  },
  {
    "content_id": 809935,
    "reference_id": 131052,
    "version": "1.0.1",
    "title": "फिलिप्पियों 2:11",
    "media_type": "Text",
    "index_reference": "50002011",
    "language": "hin",
    "review_level": "None",
    "content": "<p><strong>हर जीभ क्या </strong><span><strong>अंगीकार </strong></span><strong>करेगी?</strong></p><p><span>हर एक जीभ अंगीकार करेगी कि यीशु मसीह ही प्रभु है।</span></p>",
    "associations": {
      "passage": [
        {
          "start_ref": "50002011",
          "start_ref_usfm": "PHP 2:11",
          "end_ref": "50002011",
          "end_ref_usfm": "PHP 2:11"
        }
      ],
      "resource": []
    }
  },
  {
    "content_id": 809936,
    "reference_id": 131053,
    "version": "1.0.1",
    "title": "फिलिप्पियों 2:12",
    "media_type": "Text",
    "index_reference": "50002012",
    "language": "hin",
    "review_level": "None",
    "content": "<p><strong>फिलिप्पियों को अपने </strong><span><strong>उद्धार का कार्य कैसे पूरा करना </strong></span><strong>है?</strong></p><p>फिलिप्पियों को <span>डरते और काँपते हुए अपने-अपने उद्धार का कार्य पूरा करना है</span>।</p>",
    "associations": {
      "passage": [
        {
          "start_ref": "50002012",
          "start_ref_usfm": "PHP 2:12",
          "end_ref": "50002012",
          "end_ref_usfm": "PHP 2:12"
        }
      ],
      "resource": []
    }
  },
  {
    "content_id": 809937,
    "reference_id": 131054,
    "version": "1.0.1",
    "title": "फिलिप्पियों 2:13",
    "media_type": "Text",
    "index_reference": "50002013",
    "language": "hin",
    "review_level": "None",
    "content": "<p><strong>विश्वासियों में परमेश्वर कैसे </strong><span><strong>प्रभाव डाले </strong></span><strong>हैं?</strong></p><p>परमेश्वर विश्वासियों में <span>अपनी सुइच्छा निमित्त उनके मन में इच्छा और काम, दोनों बातों के लिए प्रभाव डाले हैं। </span></p>",
    "associations": {
      "passage": [
        {
          "start_ref": "50002013",
          "start_ref_usfm": "PHP 2:13",
          "end_ref": "50002013",
          "end_ref_usfm": "PHP 2:13"
        }
      ],
      "resource": []
    }
  },
  {
    "content_id": 809938,
    "reference_id": 131055,
    "version": "1.0.1",
    "title": "फिलिप्पियों 2:14",
    "media_type": "Text",
    "index_reference": "50002014",
    "language": "hin",
    "review_level": "None",
    "content": "<p><strong>सब काम कैसे किया जाना चाहिए?</strong></p><p><span>सब काम बिना कुड़कुड़ाए और बिना विवाद के </span>किया जाना चाहिए।</p>",
    "associations": {
      "passage": [
        {
          "start_ref": "50002014",
          "start_ref_usfm": "PHP 2:14",
          "end_ref": "50002014",
          "end_ref_usfm": "PHP 2:14"
        }
      ],
      "resource": []
    }
  },
  {
    "content_id": 809939,
    "reference_id": 131056,
    "version": "1.0.1",
    "title": "फिलिप्पियों 2:17",
    "media_type": "Text",
    "index_reference": "50002017",
    "language": "hin",
    "review_level": "None",
    "content": "<p><strong>पौलुस किस कारण से अपना लहू भी बहाने को </strong><span><strong>तैयार थे </strong></span><strong>?</strong></p><p>पौलुस फिलिप्पियों के विश्वास के बलिदान और सेवा के लिए अपना लहू भी बहाने को तैयार थे। </p>",
    "associations": {
      "passage": [
        {
          "start_ref": "50002017",
          "start_ref_usfm": "PHP 2:17",
          "end_ref": "50002017",
          "end_ref_usfm": "PHP 2:17"
        }
      ],
      "resource": []
    }
  },
  {
    "content_id": 809940,
    "reference_id": 131057,
    "version": "1.0.1",
    "title": "फिलिप्पियों 2:20",
    "media_type": "Text",
    "index_reference": "50002020",
    "language": "hin",
    "review_level": "None",
    "content": "<p><strong>तीमुथियुस पौलुस के लिए एक अद्वितीय सहायक क्यों हैं?</strong></p><p>तीमुथियुस अद्वितीय हैं क्योंकि वह <span>शुद्ध मन से </span>फिलिप्पियों की <span>चिन्ता करते हैं। </span></p>",
    "associations": {
      "passage": [
        {
          "start_ref": "50002020",
          "start_ref_usfm": "PHP 2:20",
          "end_ref": "50002020",
          "end_ref_usfm": "PHP 2:20"
        }
      ],
      "resource": []
    }
  },
  {
    "content_id": 809941,
    "reference_id": 131058,
    "version": "1.0.1",
    "title": "फिलिप्पियों 2:24",
    "media_type": "Text",
    "index_reference": "50002024",
    "language": "hin",
    "review_level": "None",
    "content": "<p><strong>क्या पौलुस फिलिप्पियों से मिलने की आशा कर रहे हैं?</strong></p><p>हाँ, पौलुस शीघ्र ही फिलिप्पियों से मिलने की आशा करते हैं।</p>",
    "associations": {
      "passage": [
        {
          "start_ref": "50002024",
          "start_ref_usfm": "PHP 2:24",
          "end_ref": "50002024",
          "end_ref_usfm": "PHP 2:24"
        }
      ],
      "resource": []
    }
  },
  {
    "content_id": 809942,
    "reference_id": 131059,
    "version": "1.0.1",
    "title": "फिलिप्पियों 2:30",
    "media_type": "Text",
    "index_reference": "50002030",
    "language": "hin",
    "review_level": "None",
    "content": "<p><strong>इपफ्रुदीतुस ने किस </strong><span><strong>काम के लिये अपने प्राणों को जोखिम में डाला</strong></span><strong>?</strong></p><p>इपफ्रुदीतुस <span>मसीह के काम के लिये अपने प्राणों पर जोखिम में डाला, ताकि जो घटी उनकी ओर से पौलुस की सेवा में हुई उसे पूरा करे</span>।</p>",
    "associations": {
      "passage": [
        {
          "start_ref": "50002030",
          "start_ref_usfm": "PHP 2:30",
          "end_ref": "50002030",
          "end_ref_usfm": "PHP 2:30"
        }
      ],
      "resource": []
    }
  },
  {
    "content_id": 809943,
    "reference_id": 131060,
    "version": "1.0.1",
    "title": "फिलिप्पियों 3:2",
    "media_type": "Text",
    "index_reference": "50003002",
    "language": "hin",
    "review_level": "None",
    "content": "<p><strong>पौलुस विश्वासियों को किससे चौकस रहने की चेतावनी देते हैं?</strong></p><p>पौलुस विश्वासियों को <span>कुत्तों</span>, <span>बुरे काम करनेवालों </span>और <span>काट-कूट करनेवालों से चौकस रहने की चेतावनी देते हैं</span>।</p>",
    "associations": {
      "passage": [
        {
          "start_ref": "50003002",
          "start_ref_usfm": "PHP 3:2",
          "end_ref": "50003002",
          "end_ref_usfm": "PHP 3:2"
        }
      ],
      "resource": []
    }
  },
  {
    "content_id": 809944,
    "reference_id": 131061,
    "version": "1.0.1",
    "title": "फिलिप्पियों 3:3",
    "media_type": "Text",
    "index_reference": "50003003",
    "language": "hin",
    "review_level": "None",
    "content": "<p><strong>पौलुस के अनुसार </strong><span><strong>यथार्थ खतनावाले</strong></span><strong> कौन हैं?</strong></p><p>पौलुस कहते हैं कि <span>यथार्थ खतनावाले वो हैं</span> <span>जो परमेश्वर के आत्मा की अगुआई से उपासना करते हैं, और मसीह यीशु पर घमण्ड करते हैं और शरीर पर भरोसा नहीं रखते हैं। </span></p>",
    "associations": {
      "passage": [
        {
          "start_ref": "50003003",
          "start_ref_usfm": "PHP 3:3",
          "end_ref": "50003003",
          "end_ref_usfm": "PHP 3:3"
        }
      ],
      "resource": []
    }
  },
  {
    "content_id": 809945,
    "reference_id": 131062,
    "version": "1.0.1",
    "title": "फिलिप्पियों 3:6",
    "media_type": "Text",
    "index_reference": "50003006",
    "language": "hin",
    "review_level": "None",
    "content": "<p><strong>पौलुस </strong><span><strong>व्यवस्था की धार्मिकता के विषय में स्वयं को </strong></span><strong>कैसा मानते हैं?</strong></p><p>पौलुस व्यवस्था की धार्मिकता के विषय में स्वयं को निर्दोष मानते हैं। </p>",
    "associations": {
      "passage": [
        {
          "start_ref": "50003006",
          "start_ref_usfm": "PHP 3:6",
          "end_ref": "50003006",
          "end_ref_usfm": "PHP 3:6"
        }
      ],
      "resource": []
    }
  },
  {
    "content_id": 809946,
    "reference_id": 131063,
    "version": "1.0.1",
    "title": "फिलिप्पियों 3:7",
    "media_type": "Text",
    "index_reference": "50003007",
    "language": "hin",
    "review_level": "None",
    "content": "<p><strong> पौलुस के अनुसार </strong><span><strong>जो बातें उन्हे लाभ की लगती थीं, मसीह के कारण वो अब उन्हें कैसा समझते हैं?</strong></span></p><p> पौलुस के अनुसार जो बातें उन्हे लाभ की लगती थीं, मसीह के कारण उसे वो अब हानी समझते हैं।</p>",
    "associations": {
      "passage": [
        {
          "start_ref": "50003007",
          "start_ref_usfm": "PHP 3:7",
          "end_ref": "50003007",
          "end_ref_usfm": "PHP 3:7"
        }
      ],
      "resource": []
    }
  },
  {
    "content_id": 809947,
    "reference_id": 131064,
    "version": "1.0.1",
    "title": "फिलिप्पियों 3:8",
    "media_type": "Text",
    "index_reference": "50003008",
    "language": "hin",
    "review_level": "None",
    "content": "<p><strong>पौलुस पिछली सब बातों को</strong><span><strong> कूड़ा क्यों समझते हैं</strong></span><strong>?</strong></p><p><span>मसीह को प्राप्त करने की इच्छा के कारण पौलुस पिछली सब बातों को कूड़ा समझते हैं</span>।</p>",
    "associations": {
      "passage": [
        {
          "start_ref": "50003008",
          "start_ref_usfm": "PHP 3:8",
          "end_ref": "50003008",
          "end_ref_usfm": "PHP 3:8"
        }
      ],
      "resource": []
    }
  },
  {
    "content_id": 809948,
    "reference_id": 131065,
    "version": "1.0.1",
    "title": "फिलिप्पियों 3:9",
    "media_type": "Text",
    "index_reference": "50003009",
    "language": "hin",
    "review_level": "None",
    "content": "<p><strong>अब पौलुस के पास कौन सी धार्मिकता है?</strong></p><p>पौलुस को अब परमेश्वर की ओर से धार्मिकता प्राप्त है जो मसीह में विश्वास करने पर मिलती है।</p>",
    "associations": {
      "passage": [
        {
          "start_ref": "50003009",
          "start_ref_usfm": "PHP 3:9",
          "end_ref": "50003009",
          "end_ref_usfm": "PHP 3:9"
        }
      ],
      "resource": []
    }
  },
  {
    "content_id": 809949,
    "reference_id": 131066,
    "version": "1.0.1",
    "title": "फिलिप्पियों 3:10",
    "media_type": "Text",
    "index_reference": "50003010",
    "language": "hin",
    "review_level": "None",
    "content": "<p><strong>पौलुस की मसीह के साथ सहभागिता किसमें है?</strong></p><p>पौलुस की मसीह के दुःखों में सहभागिता है।</p>",
    "associations": {
      "passage": [
        {
          "start_ref": "50003010",
          "start_ref_usfm": "PHP 3:10",
          "end_ref": "50003010",
          "end_ref_usfm": "PHP 3:10"
        }
      ],
      "resource": []
    }
  },
  {
    "content_id": 809950,
    "reference_id": 131067,
    "version": "1.0.1",
    "title": "फिलिप्पियों 3:12",
    "media_type": "Text",
    "index_reference": "50003012",
    "language": "hin",
    "review_level": "None",
    "content": "<p><strong>पौलुस किस </strong><span><strong>पदार्थ को पकड़ने के लिये दौड़े चले जाते हैं</strong></span><strong>?</strong></p><p>पौलुस <span>उस पदार्थ को पकड़ने के लिये दौड़े चले जाते हैं, जिसके लिये मसीह यीशु ने उन्हे पकड़ा था</span>।</p>",
    "associations": {
      "passage": [
        {
          "start_ref": "50003012",
          "start_ref_usfm": "PHP 3:12",
          "end_ref": "50003012",
          "end_ref_usfm": "PHP 3:12"
        }
      ],
      "resource": []
    }
  },
  {
    "content_id": 809951,
    "reference_id": 131068,
    "version": "1.0.1",
    "title": "फिलिप्पियों 3:14",
    "media_type": "Text",
    "index_reference": "50003014",
    "language": "hin",
    "review_level": "None",
    "content": "<p><strong>पौलुस किस ओर दौड़े चले जाते हैं?</strong></p><p>पौलुस उस <span>निशाने की ओर </span>दौड़े चले जाते हैं <span>जिसके लिये परमेश्वर ने उन्हें मसीह यीशु में ऊपर बुलाया है</span>।</p>",
    "associations": {
      "passage": [
        {
          "start_ref": "50003014",
          "start_ref_usfm": "PHP 3:14",
          "end_ref": "50003014",
          "end_ref_usfm": "PHP 3:14"
        }
      ],
      "resource": []
    }
  },
  {
    "content_id": 809952,
    "reference_id": 131069,
    "version": "1.0.1",
    "title": "फिलिप्पियों 3:17",
    "media_type": "Text",
    "index_reference": "50003017",
    "language": "hin",
    "review_level": "None",
    "content": "<p><strong>पौलुस फिलिप्पियों से किसके </strong><span><strong>उदाहरण पर </strong></span><strong>चलने के लिए कहते हैं?</strong></p><p>पौलुस फिलिप्पियों से कहते हैं कि वे उसके साथ मिलकर उनकी सी चाल चलें।</p>",
    "associations": {
      "passage": [
        {
          "start_ref": "50003017",
          "start_ref_usfm": "PHP 3:17",
          "end_ref": "50003017",
          "end_ref_usfm": "PHP 3:17"
        }
      ],
      "resource": []
    }
  },
  {
    "content_id": 809953,
    "reference_id": 131070,
    "version": "1.0.1",
    "title": "फिलिप्पियों 3:19",
    "media_type": "Text",
    "index_reference": "50003019",
    "language": "hin",
    "review_level": "None",
    "content": "<p><strong>उन लोगों का क्या परिणाम होगा जिनका ईश्वर पेट है, और जो </strong><span><strong>पृथ्वी की वस्तुओं पर मन लगाए रहते हैं</strong></span><strong>?</strong></p><p>वे लोग जिनका ईश्वर पेट है, जो पृथ्वी की वस्तुओं पर मन लगाए रहते हैं उनका अन्त विनाश है।</p>",
    "associations": {
      "passage": [
        {
          "start_ref": "50003019",
          "start_ref_usfm": "PHP 3:19",
          "end_ref": "50003019",
          "end_ref_usfm": "PHP 3:19"
        }
      ],
      "resource": []
    }
  },
  {
    "content_id": 809954,
    "reference_id": 131071,
    "version": "1.0.1",
    "title": "फिलिप्पियों 3:20",
    "media_type": "Text",
    "index_reference": "50003020",
    "language": "hin",
    "review_level": "None",
    "content": "<p><strong>पौलुस के अनुसार विश्वासियों का स्वदेश कहां पर है?</strong></p><p>पौलुस कहते हैं कि विश्वासियों का स्वदेश स्वर्ग में है।</p>",
    "associations": {
      "passage": [
        {
          "start_ref": "50003020",
          "start_ref_usfm": "PHP 3:20",
          "end_ref": "50003020",
          "end_ref_usfm": "PHP 3:20"
        }
      ],
      "resource": []
    }
  },
  {
    "content_id": 809955,
    "reference_id": 131072,
    "version": "1.0.1",
    "title": "फिलिप्पियों 3:21",
    "media_type": "Text",
    "index_reference": "50003021",
    "language": "hin",
    "review_level": "None",
    "content": "<p><strong>जब मसीह स्वर्ग से आयेंगे तो वह विश्वासियों के दीन-हीन देह के साथ क्या करेंगे?</strong></p><p>मसीह अपने प्रभाव के द्वारा विश्वासियों के दीन-हीन देह को <span>अपनी महिमा की देह के अनुकूल बना देंगें। </span></p>",
    "associations": {
      "passage": [
        {
          "start_ref": "50003021",
          "start_ref_usfm": "PHP 3:21",
          "end_ref": "50003021",
          "end_ref_usfm": "PHP 3:21"
        }
      ],
      "resource": []
    }
  },
  {
    "content_id": 809956,
    "reference_id": 131073,
    "version": "1.0.1",
    "title": "फिलिप्पियों 4:1",
    "media_type": "Text",
    "index_reference": "50004001",
    "language": "hin",
    "review_level": "None",
    "content": "<p><strong>पौलुस फिलिप्पी में अपने प्रिय भाईयों से क्या इच्छा रखते हैं?</strong></p><p>पौलुस फिलिप्पियों से चाहते हैं कि वे प्रभु मे स्थिर रहें।</p>",
    "associations": {
      "passage": [
        {
          "start_ref": "50004001",
          "start_ref_usfm": "PHP 4:1",
          "end_ref": "50004001",
          "end_ref_usfm": "PHP 4:1"
        }
      ],
      "resource": []
    }
  },
  {
    "content_id": 809957,
    "reference_id": 131074,
    "version": "1.0.1",
    "title": "फिलिप्पियों 4:2",
    "media_type": "Text",
    "index_reference": "50004002",
    "language": "hin",
    "review_level": "None",
    "content": "<p><strong>पौलुस यूओदिया और सुन्तुखे से क्या निवेदन करते हैं?</strong></p><p>पौलुस यूओदिया और सुन्तुखे से निवेदन करते हैं कि वे प्रभु में एक मन रहें।</p>",
    "associations": {
      "passage": [
        {
          "start_ref": "50004002",
          "start_ref_usfm": "PHP 4:2",
          "end_ref": "50004002",
          "end_ref_usfm": "PHP 4:2"
        }
      ],
      "resource": []
    }
  },
  {
    "content_id": 809958,
    "reference_id": 131075,
    "version": "1.0.1",
    "title": "फिलिप्पियों 4:4",
    "media_type": "Text",
    "index_reference": "50004004",
    "language": "hin",
    "review_level": "None",
    "content": "<p><strong>पौलुस फिलिप्पियों से सदा क्या करने के लिए कहते हैं?</strong></p><p>पौलुस उनसे प्रभु में सदा <span>आनन्दित </span>रहने के लिए कहते हैं।</p>",
    "associations": {
      "passage": [
        {
          "start_ref": "50004004",
          "start_ref_usfm": "PHP 4:4",
          "end_ref": "50004004",
          "end_ref_usfm": "PHP 4:4"
        }
      ],
      "resource": []
    }
  },
  {
    "content_id": 809959,
    "reference_id": 131076,
    "version": "1.0.1",
    "title": "फिलिप्पियों 4:6",
    "media_type": "Text",
    "index_reference": "50004006",
    "language": "hin",
    "review_level": "None",
    "content": "<p><strong>पौलुस चिन्ता करने के बजाय क्या करने के लिए कहते हैं?</strong></p><p>पौलुस कहते हैं कि चिन्ता करने के बजाय, हमें हमारे निवेदन धन्यवाद के साथ प्रार्थना में परमेश्वर के सम्मुख उपस्थित करना चाहिए।</p>",
    "associations": {
      "passage": [
        {
          "start_ref": "50004006",
          "start_ref_usfm": "PHP 4:6",
          "end_ref": "50004006",
          "end_ref_usfm": "PHP 4:6"
        }
      ],
      "resource": []
    }
  },
  {
    "content_id": 809960,
    "reference_id": 131077,
    "version": "1.0.1",
    "title": "फिलिप्पियों 4:7",
    "media_type": "Text",
    "index_reference": "50004007",
    "language": "hin",
    "review_level": "None",
    "content": "<p><strong>अगर हम ऐसा करेंगे, तो हमारे हृदय और विचारों की सुरक्षा कौन करेगा?</strong></p><p>अगर हम ऐसा करेंगे, तो परमेश्वर की शांति हमारे हृदय और विचारों को मसीह यीशु में सुरक्षित रखेगी।</p>",
    "associations": {
      "passage": [
        {
          "start_ref": "50004007",
          "start_ref_usfm": "PHP 4:7",
          "end_ref": "50004007",
          "end_ref_usfm": "PHP 4:7"
        }
      ],
      "resource": []
    }
  },
  {
    "content_id": 809961,
    "reference_id": 131078,
    "version": "1.0.1",
    "title": "फिलिप्पियों 4:8",
    "media_type": "Text",
    "index_reference": "50004008",
    "language": "hin",
    "review_level": "None",
    "content": "<p><strong>पौलुस किस तरह की बातों पर ध्यान लगाने के लिए कहते हैं?</strong></p><p>पौलुस कहते हैं कि उन बातों पर ध्यान लगाने के लिए कहते हैं, जो <span>सत्य, आदरणीय, उचित, पवित्र, सुहावनी, मनभावनी, सद्गुण और प्रशंसा की हैं। </span></p><p></p><p></p>",
    "associations": {
      "passage": [
        {
          "start_ref": "50004008",
          "start_ref_usfm": "PHP 4:8",
          "end_ref": "50004008",
          "end_ref_usfm": "PHP 4:8"
        }
      ],
      "resource": []
    }
  },
  {
    "content_id": 809962,
    "reference_id": 131079,
    "version": "1.0.1",
    "title": "फिलिप्पियों 4:10",
    "media_type": "Text",
    "index_reference": "50004010",
    "language": "hin",
    "review_level": "None",
    "content": "<p><strong>फिलिप्पी के लोग अब किस विषय में फिर जागृत हुए?</strong></p><p>फिलिप्पी के लोग पौलुस के विषय में फिर जागृत हुए।</p>",
    "associations": {
      "passage": [
        {
          "start_ref": "50004010",
          "start_ref_usfm": "PHP 4:10",
          "end_ref": "50004010",
          "end_ref_usfm": "PHP 4:10"
        }
      ],
      "resource": []
    }
  },
  {
    "content_id": 809963,
    "reference_id": 131080,
    "version": "1.0.1",
    "title": "फिलिप्पियों 4:11–12",
    "media_type": "Text",
    "index_reference": "50004011-50004012",
    "language": "hin",
    "review_level": "None",
    "content": "<p><strong>पौलुस ने विभिन्न दशा में क्या सीखा है?</strong></p><p>पौलुस ने बढ़ने और घटने की दशा में<span> सन्तोष रहना सीख लिया हैं </span>।</p>",
    "associations": {
      "passage": [
        {
          "start_ref": "50004011",
          "start_ref_usfm": "PHP 4:11",
          "end_ref": "50004012",
          "end_ref_usfm": "PHP 4:12"
        }
      ],
      "resource": []
    }
  },
  {
    "content_id": 809964,
    "reference_id": 131081,
    "version": "1.0.1",
    "title": "फिलिप्पियों 4:13",
    "media_type": "Text",
    "index_reference": "50004013",
    "language": "hin",
    "review_level": "None",
    "content": "<p><strong>पौलुस किस सामर्थ्य से संतुष्ट जीवन जी सकते हैं?</strong></p><p>पौलुस मसीह के द्वारा, जो उसे सामर्थ्य देते हैं, सभी दशा में संतुष्ट जीवन जी सकते हैं।</p>",
    "associations": {
      "passage": [
        {
          "start_ref": "50004013",
          "start_ref_usfm": "PHP 4:13",
          "end_ref": "50004013",
          "end_ref_usfm": "PHP 4:13"
        }
      ],
      "resource": []
    }
  },
  {
    "content_id": 809965,
    "reference_id": 131082,
    "version": "1.0.1",
    "title": "फिलिप्पियों 4:17",
    "media_type": "Text",
    "index_reference": "50004017",
    "language": "hin",
    "review_level": "None",
    "content": "<p><strong>पौलुस फिलिप्पियों के लिए कैसे फल की अपेक्षा रखते हैं?</strong></p><p>पौलुस फिलिप्पियों के लिए ऐसे फल की अपेक्षा रखते हैं <span>जो उनके लाभ के लिये बढ़ता जाए। </span></p>",
    "associations": {
      "passage": [
        {
          "start_ref": "50004017",
          "start_ref_usfm": "PHP 4:17",
          "end_ref": "50004017",
          "end_ref_usfm": "PHP 4:17"
        }
      ],
      "resource": []
    }
  },
  {
    "content_id": 809966,
    "reference_id": 131083,
    "version": "1.0.1",
    "title": "फिलिप्पियों 4:18",
    "media_type": "Text",
    "index_reference": "50004018",
    "language": "hin",
    "review_level": "None",
    "content": "<p><strong>परमेश्वर फिलिप्पियों द्वारा पौलुस को दिए गए उपहार को किस दृष्टि से देखता है?</strong></p><p>फिलिप्पियों द्वारा पौलुस को दिए गए उपहार परमेश्वर को भाता है।</p>",
    "associations": {
      "passage": [
        {
          "start_ref": "50004018",
          "start_ref_usfm": "PHP 4:18",
          "end_ref": "50004018",
          "end_ref_usfm": "PHP 4:18"
        }
      ],
      "resource": []
    }
  },
  {
    "content_id": 809967,
    "reference_id": 131084,
    "version": "1.0.1",
    "title": "फिलिप्पियों 4:19",
    "media_type": "Text",
    "index_reference": "50004019",
    "language": "hin",
    "review_level": "None",
    "content": "<p><strong>पौलुस के अनुसार फिलिप्पियों के लिए परमेश्वर क्या करेंगे?</strong></p><p>पौलुस कहते हैं कि <span>परमेश्वर अपने उस धन के अनुसार जो महिमा सहित मसीह यीशु में है उनकी हर एक घटी को पूरा करेगा</span>।</p>",
    "associations": {
      "passage": [
        {
          "start_ref": "50004019",
          "start_ref_usfm": "PHP 4:19",
          "end_ref": "50004019",
          "end_ref_usfm": "PHP 4:19"
        }
      ],
      "resource": []
    }
  },
  {
    "content_id": 809968,
    "reference_id": 131085,
    "version": "1.0.1",
    "title": "फिलिप्पियों 4:22",
    "media_type": "Text",
    "index_reference": "50004022",
    "language": "hin",
    "review_level": "None",
    "content": "<p><strong>पौलुस विशेष करके फिलिप्पियों में किसके घराने को नमस्कार कहते हैं?</strong></p><p>पौलुस <span>विशेष करके कैसर के घराने को नमस्कार कहते हैं।</span></p>",
    "associations": {
      "passage": [
        {
          "start_ref": "50004022",
          "start_ref_usfm": "PHP 4:22",
          "end_ref": "50004022",
          "end_ref_usfm": "PHP 4:22"
        }
      ],
      "resource": []
    }
  }
]