[
  {
    "content_id": 613017,
    "reference_id": 123076,
    "version": "1.0.0",
    "title": "傳道書 1:1",
    "media_type": "Text",
    "index_reference": "21001001",
    "language": "zht",
    "content": "<p><strong>這位傳道者是誰的後代？</strong></p><p>這位傳道者在耶路撒冷作王，是大衛的兒子。</p>",
    "associations": {
      "passage": [
        {
          "start_ref": "21001001",
          "start_ref_usfm": "ECC 1:1",
          "end_ref": "21001001",
          "end_ref_usfm": "ECC 1:1"
        }
      ],
      "resource": []
    }
  },
  {
    "content_id": 613018,
    "reference_id": 123077,
    "version": "1.0.0",
    "title": "傳道書 1:4",
    "media_type": "Text",
    "index_reference": "21001004",
    "language": "zht",
    "content": "<p><strong>什麼是永遠長存的？</strong></p><p>地是永遠長存的。</p>",
    "associations": {
      "passage": [
        {
          "start_ref": "21001004",
          "start_ref_usfm": "ECC 1:4",
          "end_ref": "21001004",
          "end_ref_usfm": "ECC 1:4"
        }
      ],
      "resource": []
    }
  },
  {
    "content_id": 613019,
    "reference_id": 123078,
    "version": "1.0.0",
    "title": "傳道書 1:8",
    "media_type": "Text",
    "index_reference": "21001008",
    "language": "zht",
    "content": "<p><strong>眼睛看什麼卻看不飽？</strong></p><p>眼睛看所見之物，卻看不飽。</p>",
    "associations": {
      "passage": [
        {
          "start_ref": "21001008",
          "start_ref_usfm": "ECC 1:8",
          "end_ref": "21001008",
          "end_ref_usfm": "ECC 1:8"
        }
      ],
      "resource": []
    }
  },
  {
    "content_id": 613020,
    "reference_id": 123079,
    "version": "1.0.0",
    "title": "傳道書 1:9",
    "media_type": "Text",
    "index_reference": "21001009",
    "language": "zht",
    "content": "<p><strong>何事將必行？</strong></p><p>已行過的事將必再行。</p>",
    "associations": {
      "passage": [
        {
          "start_ref": "21001009",
          "start_ref_usfm": "ECC 1:9",
          "end_ref": "21001009",
          "end_ref_usfm": "ECC 1:9"
        }
      ],
      "resource": []
    }
  },
  {
    "content_id": 613021,
    "reference_id": 123080,
    "version": "1.0.0",
    "title": "傳道書 1:13",
    "media_type": "Text",
    "index_reference": "21001013",
    "language": "zht",
    "content": "<p><strong>傳道者專心於什麼？</strong></p><p>傳道者專心用智慧尋求並查究天下所做的一切事。</p>",
    "associations": {
      "passage": [
        {
          "start_ref": "21001013",
          "start_ref_usfm": "ECC 1:13",
          "end_ref": "21001013",
          "end_ref_usfm": "ECC 1:13"
        }
      ],
      "resource": []
    }
  },
  {
    "content_id": 613022,
    "reference_id": 123081,
    "version": "1.0.0",
    "title": "傳道書 1:14",
    "media_type": "Text",
    "index_reference": "21001014",
    "language": "zht",
    "content": "<p><strong>在日光之下所做的一切事情有什麼意義？</strong></p><p>在陽光下所做的一切行為都是虛空，都是捕風。</p>",
    "associations": {
      "passage": [
        {
          "start_ref": "21001014",
          "start_ref_usfm": "ECC 1:14",
          "end_ref": "21001014",
          "end_ref_usfm": "ECC 1:14"
        }
      ],
      "resource": []
    }
  },
  {
    "content_id": 613023,
    "reference_id": 123082,
    "version": "1.0.0",
    "title": "傳道書 1:18",
    "media_type": "Text",
    "index_reference": "21001018",
    "language": "zht",
    "content": "<p><strong>哪裡多有愁煩？</strong></p><p>多有智慧，就多有愁煩。</p>",
    "associations": {
      "passage": [
        {
          "start_ref": "21001018",
          "start_ref_usfm": "ECC 1:18",
          "end_ref": "21001018",
          "end_ref_usfm": "ECC 1:18"
        }
      ],
      "resource": []
    }
  },
  {
    "content_id": 613024,
    "reference_id": 123083,
    "version": "1.0.0",
    "title": "傳道書 2:1",
    "media_type": "Text",
    "index_reference": "21002001",
    "language": "zht",
    "content": "<p><strong>什麼只是一陣短暫的微風？</strong></p><p>喜樂只是一陣短暫的微風。</p>",
    "associations": {
      "passage": [
        {
          "start_ref": "21002001",
          "start_ref_usfm": "ECC 2:1",
          "end_ref": "21002001",
          "end_ref_usfm": "ECC 2:1"
        }
      ],
      "resource": []
    }
  },
  {
    "content_id": 613025,
    "reference_id": 123084,
    "version": "1.0.0",
    "title": "傳道書 2:3",
    "media_type": "Text",
    "index_reference": "21002003",
    "language": "zht",
    "content": "<p><strong>傳道者想察究什麼？</strong></p><p>傳道者想要察究，在天下一生當行何事為美。</p>",
    "associations": {
      "passage": [
        {
          "start_ref": "21002003",
          "start_ref_usfm": "ECC 2:3",
          "end_ref": "21002003",
          "end_ref_usfm": "ECC 2:3"
        }
      ],
      "resource": []
    }
  },
  {
    "content_id": 613026,
    "reference_id": 123085,
    "version": "1.0.0",
    "title": "傳道書 2:6",
    "media_type": "Text",
    "index_reference": "21002006",
    "language": "zht",
    "content": "<p><strong>傳道者為什麼挖造水池？</strong></p><p>傳道者挖造水池，用來灌溉一片種滿樹木的森林。</p>",
    "associations": {
      "passage": [
        {
          "start_ref": "21002006",
          "start_ref_usfm": "ECC 2:6",
          "end_ref": "21002006",
          "end_ref_usfm": "ECC 2:6"
        }
      ],
      "resource": []
    }
  },
  {
    "content_id": 613027,
    "reference_id": 123086,
    "version": "1.0.0",
    "title": "傳道書 2:8",
    "media_type": "Text",
    "index_reference": "21002008",
    "language": "zht",
    "content": "<p><strong>傳道者如何得到世上男人所喜愛的物？</strong></p><p>傳道者有許多的妃嬪，他得到了世上男人所喜愛的物。</p>",
    "associations": {
      "passage": [
        {
          "start_ref": "21002008",
          "start_ref_usfm": "ECC 2:8",
          "end_ref": "21002008",
          "end_ref_usfm": "ECC 2:8"
        }
      ],
      "resource": []
    }
  },
  {
    "content_id": 613028,
    "reference_id": 123087,
    "version": "1.0.0",
    "title": "傳道書 2:10",
    "media_type": "Text",
    "index_reference": "21002010",
    "language": "zht",
    "content": "<p><strong>傳道者的心為何而快樂？</strong></p><p>傳道者的心為他一切所勞碌的快樂。</p><p></p>",
    "associations": {
      "passage": [
        {
          "start_ref": "21002010",
          "start_ref_usfm": "ECC 2:10",
          "end_ref": "21002010",
          "end_ref_usfm": "ECC 2:10"
        }
      ],
      "resource": []
    }
  },
  {
    "content_id": 613029,
    "reference_id": 123088,
    "version": "1.0.0",
    "title": "傳道書 2:11",
    "media_type": "Text",
    "index_reference": "21002011",
    "language": "zht",
    "content": "<p><strong>在哪裡毫無益處？</strong></p><p>在日光之下毫無益處。</p>",
    "associations": {
      "passage": [
        {
          "start_ref": "21002011",
          "start_ref_usfm": "ECC 2:11",
          "end_ref": "21002011",
          "end_ref_usfm": "ECC 2:11"
        }
      ],
      "resource": []
    }
  },
  {
    "content_id": 613030,
    "reference_id": 123089,
    "version": "1.0.0",
    "title": "傳道書 2:14",
    "media_type": "Text",
    "index_reference": "21002014",
    "language": "zht",
    "content": "<p><strong>每個人的未來會是什麼？</strong></p><p>每個人都有相同的命運。</p>",
    "associations": {
      "passage": [
        {
          "start_ref": "21002014",
          "start_ref_usfm": "ECC 2:14",
          "end_ref": "21002014",
          "end_ref_usfm": "ECC 2:14"
        }
      ],
      "resource": []
    }
  },
  {
    "content_id": 613031,
    "reference_id": 123090,
    "version": "1.0.0",
    "title": "傳道書 2:16",
    "media_type": "Text",
    "index_reference": "21002016",
    "language": "zht",
    "content": "<p><strong>誰不會被長久記念？</strong></p><p>智慧人和愚昧人一樣，無人長久記念。</p>",
    "associations": {
      "passage": [
        {
          "start_ref": "21002016",
          "start_ref_usfm": "ECC 2:16",
          "end_ref": "21002016",
          "end_ref_usfm": "ECC 2:16"
        }
      ],
      "resource": []
    }
  },
  {
    "content_id": 613032,
    "reference_id": 123091,
    "version": "1.0.0",
    "title": "傳道書 2:18",
    "media_type": "Text",
    "index_reference": "21002018",
    "language": "zht",
    "content": "<p><strong>為什麼傳道者恨惡他一切的勞碌成果？</strong></p><p>傳道者恨惡他一切的勞碌成果，因為他得來的必留給他以後的人。</p>",
    "associations": {
      "passage": [
        {
          "start_ref": "21002018",
          "start_ref_usfm": "ECC 2:18",
          "end_ref": "21002018",
          "end_ref_usfm": "ECC 2:18"
        }
      ],
      "resource": []
    }
  },
  {
    "content_id": 613033,
    "reference_id": 123092,
    "version": "1.0.0",
    "title": "傳道書 2:20",
    "media_type": "Text",
    "index_reference": "21002020",
    "language": "zht",
    "content": "<p><strong>傳道者對他所勞碌的一切工作，心裏有什麼感覺？</strong></p><p>傳道者對他所勞碌的一切工作，心便感到絕望。</p>",
    "associations": {
      "passage": [
        {
          "start_ref": "21002020",
          "start_ref_usfm": "ECC 2:20",
          "end_ref": "21002020",
          "end_ref_usfm": "ECC 2:20"
        }
      ],
      "resource": []
    }
  },
  {
    "content_id": 613034,
    "reference_id": 123093,
    "version": "1.0.0",
    "title": "傳道書 2:23",
    "media_type": "Text",
    "index_reference": "21002023",
    "language": "zht",
    "content": "<p><strong>勞苦的工作者為什麼在夜間心也不安？</strong></p><p>因為他日日的勞苦是憂慮且愁煩，連夜間心也不安。</p>",
    "associations": {
      "passage": [
        {
          "start_ref": "21002023",
          "start_ref_usfm": "ECC 2:23",
          "end_ref": "21002023",
          "end_ref_usfm": "ECC 2:23"
        }
      ],
      "resource": []
    }
  },
  {
    "content_id": 613035,
    "reference_id": 123094,
    "version": "1.0.0",
    "title": "傳道書 2:24",
    "media_type": "Text",
    "index_reference": "21002024",
    "language": "zht",
    "content": "<p><strong>人莫強如什麼？</strong></p><p>人莫強如吃喝，且在勞碌中享福。</p>",
    "associations": {
      "passage": [
        {
          "start_ref": "21002024",
          "start_ref_usfm": "ECC 2:24",
          "end_ref": "21002024",
          "end_ref_usfm": "ECC 2:24"
        }
      ],
      "resource": []
    }
  },
  {
    "content_id": 613036,
    "reference_id": 123095,
    "version": "1.0.0",
    "title": "傳道書 2:26",
    "media_type": "Text",
    "index_reference": "21002026",
    "language": "zht",
    "content": "<p><strong>神給罪人什麼？</strong></p><p>對於罪人，神叫他們做收聚和堆積的工作，以便將所收聚的、所堆積的歸給神所喜悅的人。</p>",
    "associations": {
      "passage": [
        {
          "start_ref": "21002026",
          "start_ref_usfm": "ECC 2:26",
          "end_ref": "21002026",
          "end_ref_usfm": "ECC 2:26"
        }
      ],
      "resource": []
    }
  },
  {
    "content_id": 613037,
    "reference_id": 123096,
    "version": "1.0.0",
    "title": "傳道書 3:1",
    "media_type": "Text",
    "index_reference": "21003001",
    "language": "zht",
    "content": "<p><strong>哪些事情是有定期的？</strong></p><p>凡事都有定期。</p>",
    "associations": {
      "passage": [
        {
          "start_ref": "21003001",
          "start_ref_usfm": "ECC 3:1",
          "end_ref": "21003001",
          "end_ref_usfm": "ECC 3:1"
        }
      ],
      "resource": []
    }
  },
  {
    "content_id": 613038,
    "reference_id": 123097,
    "version": "1.0.0",
    "title": "傳道書 3:10",
    "media_type": "Text",
    "index_reference": "21003010",
    "language": "zht",
    "content": "<p><strong>傳道者見到了什麼？</strong></p><p>傳道者見神叫世人勞苦工作。</p>",
    "associations": {
      "passage": [
        {
          "start_ref": "21003010",
          "start_ref_usfm": "ECC 3:10",
          "end_ref": "21003010",
          "end_ref_usfm": "ECC 3:10"
        }
      ],
      "resource": []
    }
  },
  {
    "content_id": 613039,
    "reference_id": 123098,
    "version": "1.0.0",
    "title": "傳道書 3:11",
    "media_type": "Text",
    "index_reference": "21003011",
    "language": "zht",
    "content": "<p><strong>神將什麼﻿﻿安置在世人心裏？</strong></p><p>神將永生﻿﻿安置在世人心裏。</p><p></p>",
    "associations": {
      "passage": [
        {
          "start_ref": "21003011",
          "start_ref_usfm": "ECC 3:11",
          "end_ref": "21003011",
          "end_ref_usfm": "ECC 3:11"
        }
      ],
      "resource": []
    }
  },
  {
    "content_id": 613040,
    "reference_id": 123099,
    "version": "1.0.0",
    "title": "傳道書 3:13",
    "media_type": "Text",
    "index_reference": "21003013",
    "language": "zht",
    "content": "<p><strong>神的恩賜是什麼？</strong></p><p>在一切勞碌中享福，這是神的恩賜。</p>",
    "associations": {
      "passage": [
        {
          "start_ref": "21003013",
          "start_ref_usfm": "ECC 3:13",
          "end_ref": "21003013",
          "end_ref_usfm": "ECC 3:13"
        }
      ],
      "resource": []
    }
  },
  {
    "content_id": 613041,
    "reference_id": 123100,
    "version": "1.0.0",
    "title": "傳道書 3:14",
    "media_type": "Text",
    "index_reference": "21003014",
    "language": "zht",
    "content": "<p><strong>神一切所做的，為什麼無法增添也無法減少？</strong></p><p>無所增添，無所減少，因為神一切所做的都已完成。</p>",
    "associations": {
      "passage": [
        {
          "start_ref": "21003014",
          "start_ref_usfm": "ECC 3:14",
          "end_ref": "21003014",
          "end_ref_usfm": "ECC 3:14"
        }
      ],
      "resource": []
    }
  },
  {
    "content_id": 613042,
    "reference_id": 123101,
    "version": "1.0.0",
    "title": "傳道書 3:16",
    "media_type": "Text",
    "index_reference": "21003016",
    "language": "zht",
    "content": "<p><strong>在公義之處也常有什麼？</strong></p><p>在公義之處也有奸惡。</p>",
    "associations": {
      "passage": [
        {
          "start_ref": "21003016",
          "start_ref_usfm": "ECC 3:16",
          "end_ref": "21003016",
          "end_ref_usfm": "ECC 3:16"
        }
      ],
      "resource": []
    }
  },
  {
    "content_id": 613043,
    "reference_id": 123102,
    "version": "1.0.0",
    "title": "傳道書 3:19–20",
    "media_type": "Text",
    "index_reference": "21003019-21003020",
    "language": "zht",
    "content": "<p><strong>世人如何與獸相似？</strong></p><p>獸怎樣死，人也怎樣死，氣息都是一樣。都是出於塵土，也都歸於塵土。</p>",
    "associations": {
      "passage": [
        {
          "start_ref": "21003019",
          "start_ref_usfm": "ECC 3:19",
          "end_ref": "21003020",
          "end_ref_usfm": "ECC 3:20"
        }
      ],
      "resource": []
    }
  },
  {
    "content_id": 613044,
    "reference_id": 123103,
    "version": "1.0.0",
    "title": "傳道書 3:22",
    "media_type": "Text",
    "index_reference": "21003022",
    "language": "zht",
    "content": "<p><strong>每個人的使命是什麼？</strong></p><p>每個人的使命是在他經營的事上喜樂。</p>",
    "associations": {
      "passage": [
        {
          "start_ref": "21003022",
          "start_ref_usfm": "ECC 3:22",
          "end_ref": "21003022",
          "end_ref_usfm": "ECC 3:22"
        }
      ],
      "resource": []
    }
  },
  {
    "content_id": 613045,
    "reference_id": 123104,
    "version": "1.0.0",
    "title": "傳道書 4:1",
    "media_type": "Text",
    "index_reference": "21004001",
    "language": "zht",
    "content": "<p><strong>有什麼是無人安慰的？</strong></p><p>受欺壓的人流淚，無人安慰。</p>",
    "associations": {
      "passage": [
        {
          "start_ref": "21004001",
          "start_ref_usfm": "ECC 4:1",
          "end_ref": "21004001",
          "end_ref_usfm": "ECC 4:1"
        }
      ],
      "resource": []
    }
  },
  {
    "content_id": 613046,
    "reference_id": 123105,
    "version": "1.0.0",
    "title": "傳道書 4:3",
    "media_type": "Text",
    "index_reference": "21004003",
    "language": "zht",
    "content": "<p><strong>誰比那還活著的活人和那早已死的死人更強？</strong></p><p>那未曾生的人，比還活著的活人和那早已死的死人更強。</p>",
    "associations": {
      "passage": [
        {
          "start_ref": "21004003",
          "start_ref_usfm": "ECC 4:3",
          "end_ref": "21004003",
          "end_ref_usfm": "ECC 4:3"
        }
      ],
      "resource": []
    }
  },
  {
    "content_id": 613047,
    "reference_id": 123106,
    "version": "1.0.0",
    "title": "傳道書 4:6",
    "media_type": "Text",
    "index_reference": "21004006",
    "language": "zht",
    "content": "<p><strong>有什麼強如滿了兩把，卻勞碌捕風呢？</strong></p><p>滿了一把，得享安靜，強如滿了兩把，卻勞碌捕風。</p>",
    "associations": {
      "passage": [
        {
          "start_ref": "21004006",
          "start_ref_usfm": "ECC 4:6",
          "end_ref": "21004006",
          "end_ref_usfm": "ECC 4:6"
        }
      ],
      "resource": []
    }
  },
  {
    "content_id": 613048,
    "reference_id": 123107,
    "version": "1.0.0",
    "title": "傳道書 4:9–10",
    "media_type": "Text",
    "index_reference": "21004009-21004010",
    "language": "zht",
    "content": "<p><strong>兩個人為什麼總比一個人好，特別是在一個人跌倒時？</strong></p><p>兩個人總比一個人好，因為若是一個人跌倒了，另一個人可以扶起他的同伴。</p>",
    "associations": {
      "passage": [
        {
          "start_ref": "21004009",
          "start_ref_usfm": "ECC 4:9",
          "end_ref": "21004010",
          "end_ref_usfm": "ECC 4:10"
        }
      ],
      "resource": []
    }
  },
  {
    "content_id": 613049,
    "reference_id": 123108,
    "version": "1.0.0",
    "title": "傳道書 4:12",
    "media_type": "Text",
    "index_reference": "21004012",
    "language": "zht",
    "content": "<p><strong>什麼是不容易被折斷的？</strong></p><p>三股合成的繩子不容易折斷。</p>",
    "associations": {
      "passage": [
        {
          "start_ref": "21004012",
          "start_ref_usfm": "ECC 4:12",
          "end_ref": "21004012",
          "end_ref_usfm": "ECC 4:12"
        }
      ],
      "resource": []
    }
  },
  {
    "content_id": 613050,
    "reference_id": 123109,
    "version": "1.0.0",
    "title": "傳道書 4:13",
    "media_type": "Text",
    "index_reference": "21004013",
    "language": "zht",
    "content": "<p><strong>成為什麼勝過成為年老的愚昧王？</strong></p><p>成為貧窮而有智慧的少年人，勝過成為年老的愚昧王。</p>",
    "associations": {
      "passage": [
        {
          "start_ref": "21004013",
          "start_ref_usfm": "ECC 4:13",
          "end_ref": "21004013",
          "end_ref_usfm": "ECC 4:13"
        }
      ],
      "resource": []
    }
  },
  {
    "content_id": 613051,
    "reference_id": 123110,
    "version": "1.0.0",
    "title": "傳道書 4:16",
    "media_type": "Text",
    "index_reference": "21004016",
    "language": "zht",
    "content": "<p><strong>對與新王，百姓想要做什麼？</strong></p><p>百姓都要隨從那新王。</p>",
    "associations": {
      "passage": [
        {
          "start_ref": "21004016",
          "start_ref_usfm": "ECC 4:16",
          "end_ref": "21004016",
          "end_ref_usfm": "ECC 4:16"
        }
      ],
      "resource": []
    }
  },
  {
    "content_id": 613052,
    "reference_id": 123111,
    "version": "1.0.0",
    "title": "傳道書 5:1",
    "media_type": "Text",
    "index_reference": "21005001",
    "language": "zht",
    "content": "<p><strong>眾人為什麼當去神的殿？</strong></p><p>眾人當去神的殿去近前聽。</p>",
    "associations": {
      "passage": [
        {
          "start_ref": "21005001",
          "start_ref_usfm": "ECC 5:1",
          "end_ref": "21005001",
          "end_ref_usfm": "ECC 5:1"
        }
      ],
      "resource": []
    }
  },
  {
    "content_id": 613053,
    "reference_id": 123112,
    "version": "1.0.0",
    "title": "傳道書 5:2",
    "media_type": "Text",
    "index_reference": "21005002",
    "language": "zht",
    "content": "<p><strong>為何眾人的言語要寡少？</strong></p><p>因為神在天上，眾人在地下，所以眾人的言語要寡少。</p>",
    "associations": {
      "passage": [
        {
          "start_ref": "21005002",
          "start_ref_usfm": "ECC 5:2",
          "end_ref": "21005002",
          "end_ref_usfm": "ECC 5:2"
        }
      ],
      "resource": []
    }
  },
  {
    "content_id": 613054,
    "reference_id": 123113,
    "version": "1.0.0",
    "title": "傳道書 5:5",
    "media_type": "Text",
    "index_reference": "21005005",
    "language": "zht",
    "content": "<p><strong>一個人許願不還，不如怎樣？</strong></p><p>一個人許願不還，不如不許。</p>",
    "associations": {
      "passage": [
        {
          "start_ref": "21005005",
          "start_ref_usfm": "ECC 5:5",
          "end_ref": "21005005",
          "end_ref_usfm": "ECC 5:5"
        }
      ],
      "resource": []
    }
  },
  {
    "content_id": 613055,
    "reference_id": 123114,
    "version": "1.0.0",
    "title": "傳道書 5:8",
    "media_type": "Text",
    "index_reference": "21005008",
    "language": "zht",
    "content": "<p><strong>若有人見窮人受欺壓，並被奪去公義公平的事，為什麼不要因此詫異，彷彿沒有人知道一樣？</strong></p><p>若有人見窮人受欺壓，並被奪去公義公平的事，不要因此詫異，因有高過居高位的人在鑒察，在他們以上還有更高的。</p>",
    "associations": {
      "passage": [
        {
          "start_ref": "21005008",
          "start_ref_usfm": "ECC 5:8",
          "end_ref": "21005008",
          "end_ref_usfm": "ECC 5:8"
        }
      ],
      "resource": []
    }
  },
  {
    "content_id": 613056,
    "reference_id": 123115,
    "version": "1.0.0",
    "title": "傳道書 5:11",
    "media_type": "Text",
    "index_reference": "21005011",
    "language": "zht",
    "content": "<p><strong>隨著繁榮增加會發生什麼情況？</strong></p><p>隨著繁榮增加，消費繁榮的人也增加。</p>",
    "associations": {
      "passage": [
        {
          "start_ref": "21005011",
          "start_ref_usfm": "ECC 5:11",
          "end_ref": "21005011",
          "end_ref_usfm": "ECC 5:11"
        }
      ],
      "resource": []
    }
  },
  {
    "content_id": 613057,
    "reference_id": 123116,
    "version": "1.0.0",
    "title": "傳道書 5:12",
    "media_type": "Text",
    "index_reference": "21005012",
    "language": "zht",
    "content": "<p><strong>是什麼不容富足的人睡得香甜？</strong></p><p>富足人的豐滿不容他睡得香甜。</p>",
    "associations": {
      "passage": [
        {
          "start_ref": "21005012",
          "start_ref_usfm": "ECC 5:12",
          "end_ref": "21005012",
          "end_ref_usfm": "ECC 5:12"
        }
      ],
      "resource": []
    }
  },
  {
    "content_id": 613058,
    "reference_id": 123117,
    "version": "1.0.0",
    "title": "傳道書 5:14",
    "media_type": "Text",
    "index_reference": "21005014",
    "language": "zht",
    "content": "<p><strong>財主因遭遇禍患而失去資財時，會發生什麼事？</strong></p><p>財主因遭遇禍患，他的資財就消滅，他所生的兒子，手裏也一無所有。</p>",
    "associations": {
      "passage": [
        {
          "start_ref": "21005014",
          "start_ref_usfm": "ECC 5:14",
          "end_ref": "21005014",
          "end_ref_usfm": "ECC 5:14"
        }
      ],
      "resource": []
    }
  },
  {
    "content_id": 613059,
    "reference_id": 123118,
    "version": "1.0.0",
    "title": "傳道書 5:15",
    "media_type": "Text",
    "index_reference": "21005015",
    "language": "zht",
    "content": "<p><strong>一個人怎樣出生，又怎樣死去？</strong></p><p>一個人從母胎赤身而來，也必照樣赤身而去。</p>",
    "associations": {
      "passage": [
        {
          "start_ref": "21005015",
          "start_ref_usfm": "ECC 5:15",
          "end_ref": "21005015",
          "end_ref_usfm": "ECC 5:15"
        }
      ],
      "resource": []
    }
  },
  {
    "content_id": 613060,
    "reference_id": 123119,
    "version": "1.0.0",
    "title": "傳道書 5:20",
    "media_type": "Text",
    "index_reference": "21005020",
    "language": "zht",
    "content": "<p><strong>為什麼這人不多思念自己一生的年日？</strong></p><p>他不多思念自己一生的年日，因為神使他在勞碌中喜樂。</p>",
    "associations": {
      "passage": [
        {
          "start_ref": "21005020",
          "start_ref_usfm": "ECC 5:20",
          "end_ref": "21005020",
          "end_ref_usfm": "ECC 5:20"
        }
      ],
      "resource": []
    }
  },
  {
    "content_id": 613061,
    "reference_id": 123120,
    "version": "1.0.0",
    "title": "傳道書 6:1–2",
    "media_type": "Text",
    "index_reference": "21006001-21006002",
    "language": "zht",
    "content": "<p><strong>傳道者見到了什麼禍患？</strong></p><p>就是人蒙神賜他資財、豐富、尊榮，以致他心裏所願的一樣都不缺，只是神使他不能吃用，反有外人來吃用。</p>",
    "associations": {
      "passage": [
        {
          "start_ref": "21006001",
          "start_ref_usfm": "ECC 6:1",
          "end_ref": "21006002",
          "end_ref_usfm": "ECC 6:2"
        }
      ],
      "resource": []
    }
  },
  {
    "content_id": 613062,
    "reference_id": 123121,
    "version": "1.0.0",
    "title": "傳道書 6:3",
    "media_type": "Text",
    "index_reference": "21006003",
    "language": "zht",
    "content": "<p><strong>如果一個人心裏不得滿享福樂，又不得尊榮埋葬，那麽誰比他倒好呢？</strong></p><p>如果一個人心裏不得滿享福樂，又不得尊榮埋葬，那不到期而夭折的胎兒比他倒好。</p>",
    "associations": {
      "passage": [
        {
          "start_ref": "21006003",
          "start_ref_usfm": "ECC 6:3",
          "end_ref": "21006003",
          "end_ref_usfm": "ECC 6:3"
        }
      ],
      "resource": []
    }
  },
  {
    "content_id": 613063,
    "reference_id": 123122,
    "version": "1.0.0",
    "title": "傳道書 6:6",
    "media_type": "Text",
    "index_reference": "21006006",
    "language": "zht",
    "content": "<p><strong>那人雖然活了兩千年，卻不享福，他會去向哪裏呢？</strong></p><p>那人雖然活了兩千年，卻不享福，他與眾人都歸向同一個地方去。</p>",
    "associations": {
      "passage": [
        {
          "start_ref": "21006006",
          "start_ref_usfm": "ECC 6:6",
          "end_ref": "21006006",
          "end_ref_usfm": "ECC 6:6"
        }
      ],
      "resource": []
    }
  },
  {
    "content_id": 613064,
    "reference_id": 123123,
    "version": "1.0.0",
    "title": "傳道書 6:7",
    "media_type": "Text",
    "index_reference": "21006007",
    "language": "zht",
    "content": "<p><strong>人的勞碌都為口腹，卻發生什麼事？</strong></p><p>人的勞碌都為口腹，心裏卻不知足。</p>",
    "associations": {
      "passage": [
        {
          "start_ref": "21006007",
          "start_ref_usfm": "ECC 6:7",
          "end_ref": "21006007",
          "end_ref_usfm": "ECC 6:7"
        }
      ],
      "resource": []
    }
  },
  {
    "content_id": 613065,
    "reference_id": 123124,
    "version": "1.0.0",
    "title": "傳道書 6:11",
    "media_type": "Text",
    "index_reference": "21006011",
    "language": "zht",
    "content": "<p><strong>話語加增會發生什麼事？</strong></p><p>話語加增，虛浮的事也就越多。</p>",
    "associations": {
      "passage": [
        {
          "start_ref": "21006011",
          "start_ref_usfm": "ECC 6:11",
          "end_ref": "21006011",
          "end_ref_usfm": "ECC 6:11"
        }
      ],
      "resource": []
    }
  },
  {
    "content_id": 613066,
    "reference_id": 123125,
    "version": "1.0.0",
    "title": "傳道書 7:2",
    "media_type": "Text",
    "index_reference": "21007002",
    "language": "zht",
    "content": "<p><strong>為什麼往遭喪的家去，強如往宴樂的家去呢？</strong></p><p>往遭喪的家去，強如往宴樂的家去，因為死是眾人的結局。</p>",
    "associations": {
      "passage": [
        {
          "start_ref": "21007002",
          "start_ref_usfm": "ECC 7:2",
          "end_ref": "21007002",
          "end_ref_usfm": "ECC 7:2"
        }
      ],
      "resource": []
    }
  },
  {
    "content_id": 613067,
    "reference_id": 123126,
    "version": "1.0.0",
    "title": "傳道書 7:4",
    "media_type": "Text",
    "index_reference": "21007004",
    "language": "zht",
    "content": "<p><strong>智慧人的心在哪裡？</strong></p><p>智慧人的心在遭喪之家。</p>",
    "associations": {
      "passage": [
        {
          "start_ref": "21007004",
          "start_ref_usfm": "ECC 7:4",
          "end_ref": "21007004",
          "end_ref_usfm": "ECC 7:4"
        }
      ],
      "resource": []
    }
  },
  {
    "content_id": 613068,
    "reference_id": 123127,
    "version": "1.0.0",
    "title": "傳道書 7:6",
    "media_type": "Text",
    "index_reference": "21007006",
    "language": "zht",
    "content": "<p><strong>愚昧人的笑聲像什麼？</strong></p><p>愚昧人的笑聲，好像鍋下燒荊棘的爆聲。</p>",
    "associations": {
      "passage": [
        {
          "start_ref": "21007006",
          "start_ref_usfm": "ECC 7:6",
          "end_ref": "21007006",
          "end_ref_usfm": "ECC 7:6"
        }
      ],
      "resource": []
    }
  },
  {
    "content_id": 613069,
    "reference_id": 123128,
    "version": "1.0.0",
    "title": "傳道書 7:7",
    "media_type": "Text",
    "index_reference": "21007007",
    "language": "zht",
    "content": "<p><strong>是什麼使智慧人變為愚妄？</strong></p><p>勒索使智慧人變為愚妄。</p>",
    "associations": {
      "passage": [
        {
          "start_ref": "21007007",
          "start_ref_usfm": "ECC 7:7",
          "end_ref": "21007007",
          "end_ref_usfm": "ECC 7:7"
        }
      ],
      "resource": []
    }
  },
  {
    "content_id": 613070,
    "reference_id": 123129,
    "version": "1.0.0",
    "title": "傳道書 7:9",
    "media_type": "Text",
    "index_reference": "21007009",
    "language": "zht",
    "content": "<p><strong>為什麼人不要心裏急躁惱怒？</strong></p><p>人不要心裏急躁惱怒，因為惱怒存在愚昧人的懷中。</p>",
    "associations": {
      "passage": [
        {
          "start_ref": "21007009",
          "start_ref_usfm": "ECC 7:9",
          "end_ref": "21007009",
          "end_ref_usfm": "ECC 7:9"
        }
      ],
      "resource": []
    }
  },
  {
    "content_id": 613071,
    "reference_id": 123130,
    "version": "1.0.0",
    "title": "傳道書 7:12",
    "media_type": "Text",
    "index_reference": "21007012",
    "language": "zht",
    "content": "<p><strong>智慧如何比銀錢更好？</strong></p><p>因為智慧護庇人，好像銀錢護庇人一樣。 惟獨智慧能保全智慧人的生命。</p>",
    "associations": {
      "passage": [
        {
          "start_ref": "21007012",
          "start_ref_usfm": "ECC 7:12",
          "end_ref": "21007012",
          "end_ref_usfm": "ECC 7:12"
        }
      ],
      "resource": []
    }
  },
  {
    "content_id": 613072,
    "reference_id": 123131,
    "version": "1.0.0",
    "title": "傳道書 7:14",
    "media_type": "Text",
    "index_reference": "21007014",
    "language": "zht",
    "content": "<p><strong>遇亨通的日子，人當如何生活？</strong></p><p>遇亨通的日子，人當喜樂。</p>",
    "associations": {
      "passage": [
        {
          "start_ref": "21007014",
          "start_ref_usfm": "ECC 7:14",
          "end_ref": "21007014",
          "end_ref_usfm": "ECC 7:14"
        }
      ],
      "resource": []
    }
  },
  {
    "content_id": 613073,
    "reference_id": 123132,
    "version": "1.0.0",
    "title": "傳道書 7:15",
    "media_type": "Text",
    "index_reference": "21007015",
    "language": "zht",
    "content": "<p><strong>傳道者見到惡人發生了什麼事？</strong></p><p>傳道者見到惡人行惡，倒享長壽。</p>",
    "associations": {
      "passage": [
        {
          "start_ref": "21007015",
          "start_ref_usfm": "ECC 7:15",
          "end_ref": "21007015",
          "end_ref_usfm": "ECC 7:15"
        }
      ],
      "resource": []
    }
  },
  {
    "content_id": 613074,
    "reference_id": 123133,
    "version": "1.0.0",
    "title": "傳道書 7:18",
    "media_type": "Text",
    "index_reference": "21007018",
    "language": "zht",
    "content": "<p><strong>敬畏神的人會發生什麼事？</strong></p><p>敬畏神的人會履行他所有的義務。</p>",
    "associations": {
      "passage": [
        {
          "start_ref": "21007018",
          "start_ref_usfm": "ECC 7:18",
          "end_ref": "21007018",
          "end_ref_usfm": "ECC 7:18"
        }
      ],
      "resource": []
    }
  },
  {
    "content_id": 613075,
    "reference_id": 123134,
    "version": "1.0.0",
    "title": "傳道書 7:21",
    "media_type": "Text",
    "index_reference": "21007021",
    "language": "zht",
    "content": "<p><strong>人為什麼不要把別人所說的一切話放在心上？</strong></p><p>人不要把別人所說的一切話都放在心上，恐怕聽見他們的僕人咒詛他們。</p>",
    "associations": {
      "passage": [
        {
          "start_ref": "21007021",
          "start_ref_usfm": "ECC 7:21",
          "end_ref": "21007021",
          "end_ref_usfm": "ECC 7:21"
        }
      ],
      "resource": []
    }
  },
  {
    "content_id": 613076,
    "reference_id": 123135,
    "version": "1.0.0",
    "title": "傳道書 7:24",
    "media_type": "Text",
    "index_reference": "21007024",
    "language": "zht",
    "content": "<p><strong>智慧在哪裡呢？</strong></p><p>智慧離得很遠。</p>",
    "associations": {
      "passage": [
        {
          "start_ref": "21007024",
          "start_ref_usfm": "ECC 7:24",
          "end_ref": "21007024",
          "end_ref_usfm": "ECC 7:24"
        }
      ],
      "resource": []
    }
  },
  {
    "content_id": 613077,
    "reference_id": 123136,
    "version": "1.0.0",
    "title": "傳道書 7:26",
    "media_type": "Text",
    "index_reference": "21007026",
    "language": "zht",
    "content": "<p><strong>有罪的人被誰纏住了？</strong></p><p>有罪的人被那心是網羅，手是鎖鍊的婦人纏住了。</p>",
    "associations": {
      "passage": [
        {
          "start_ref": "21007026",
          "start_ref_usfm": "ECC 7:26",
          "end_ref": "21007026",
          "end_ref_usfm": "ECC 7:26"
        }
      ],
      "resource": []
    }
  },
  {
    "content_id": 613078,
    "reference_id": 123137,
    "version": "1.0.0",
    "title": "傳道書 7:28",
    "media_type": "Text",
    "index_reference": "21007028",
    "language": "zht",
    "content": "<p><strong>雖然傳道者在一千男子中，找到一個正直人，但他沒有找到什麼？</strong></p><p>傳道者在一千男子中，找到一個正直人，但在眾女子中，他沒有找到一個正直人。</p>",
    "associations": {
      "passage": [
        {
          "start_ref": "21007028",
          "start_ref_usfm": "ECC 7:28",
          "end_ref": "21007028",
          "end_ref_usfm": "ECC 7:28"
        }
      ],
      "resource": []
    }
  },
  {
    "content_id": 613079,
    "reference_id": 123138,
    "version": "1.0.0",
    "title": "傳道書 8:1",
    "media_type": "Text",
    "index_reference": "21008001",
    "language": "zht",
    "content": "<p><strong>什麼是智慧人？</strong></p><p>智慧人知道生命中事件的意義。</p>",
    "associations": {
      "passage": [
        {
          "start_ref": "21008001",
          "start_ref_usfm": "ECC 8:1",
          "end_ref": "21008001",
          "end_ref_usfm": "ECC 8:1"
        }
      ],
      "resource": []
    }
  },
  {
    "content_id": 613080,
    "reference_id": 123139,
    "version": "1.0.0",
    "title": "傳道書 8:3",
    "media_type": "Text",
    "index_reference": "21008003",
    "language": "zht",
    "content": "<p><strong>人為什麼不要急躁離開王的面前，不要固執行惡？</strong></p><p>人不要急躁離開王的面前，不要固執行惡，因為王凡事都隨自己的心意而行。</p>",
    "associations": {
      "passage": [
        {
          "start_ref": "21008003",
          "start_ref_usfm": "ECC 8:3",
          "end_ref": "21008003",
          "end_ref_usfm": "ECC 8:3"
        }
      ],
      "resource": []
    }
  },
  {
    "content_id": 613081,
    "reference_id": 123140,
    "version": "1.0.0",
    "title": "傳道書 8:5",
    "media_type": "Text",
    "index_reference": "21008005",
    "language": "zht",
    "content": "<p><strong>誰必不經歷禍患？</strong></p><p>凡遵守王命令的人，必不經歷禍患。</p>",
    "associations": {
      "passage": [
        {
          "start_ref": "21008005",
          "start_ref_usfm": "ECC 8:5",
          "end_ref": "21008005",
          "end_ref_usfm": "ECC 8:5"
        }
      ],
      "resource": []
    }
  },
  {
    "content_id": 613082,
    "reference_id": 123141,
    "version": "1.0.0",
    "title": "傳道書 8:8",
    "media_type": "Text",
    "index_reference": "21008008",
    "language": "zht",
    "content": "<p><strong>無人有權力掌管什麼？</strong></p><p>無人有權力掌管生命的氣息，停止呼吸，也無人有權力掌管死亡的那一天。</p>",
    "associations": {
      "passage": [
        {
          "start_ref": "21008008",
          "start_ref_usfm": "ECC 8:8",
          "end_ref": "21008008",
          "end_ref_usfm": "ECC 8:8"
        }
      ],
      "resource": []
    }
  },
  {
    "content_id": 613083,
    "reference_id": 123142,
    "version": "1.0.0",
    "title": "傳道書 8:10",
    "media_type": "Text",
    "index_reference": "21008010",
    "language": "zht",
    "content": "<p><strong>惡人被誰稱讚？</strong></p><p>惡人在他們行惡的城中被人稱讚。</p>",
    "associations": {
      "passage": [
        {
          "start_ref": "21008010",
          "start_ref_usfm": "ECC 8:10",
          "end_ref": "21008010",
          "end_ref_usfm": "ECC 8:10"
        }
      ],
      "resource": []
    }
  },
  {
    "content_id": 613084,
    "reference_id": 123143,
    "version": "1.0.0",
    "title": "傳道書 8:12",
    "media_type": "Text",
    "index_reference": "21008012",
    "language": "zht",
    "content": "<p><strong>即使罪人作惡百次，仍然長壽，那麼敬畏神的人會怎樣呢？</strong></p><p>罪人雖然作惡百次，倒享長久的年日，但那敬畏神的人，就是在神面前尊崇祂的人，終久必得享福樂。</p>",
    "associations": {
      "passage": [
        {
          "start_ref": "21008012",
          "start_ref_usfm": "ECC 8:12",
          "end_ref": "21008012",
          "end_ref_usfm": "ECC 8:12"
        }
      ],
      "resource": []
    }
  },
  {
    "content_id": 613085,
    "reference_id": 123144,
    "version": "1.0.0",
    "title": "傳道書 8:15",
    "media_type": "Text",
    "index_reference": "21008015",
    "language": "zht",
    "content": "<p><strong>傳道者為什麼稱讚快樂？</strong></p><p>傳道者稱讚快樂，因為人在日光之下，莫強如吃喝快樂。</p>",
    "associations": {
      "passage": [
        {
          "start_ref": "21008015",
          "start_ref_usfm": "ECC 8:15",
          "end_ref": "21008015",
          "end_ref_usfm": "ECC 8:15"
        }
      ],
      "resource": []
    }
  },
  {
    "content_id": 613086,
    "reference_id": 123145,
    "version": "1.0.0",
    "title": "傳道書 8:17",
    "media_type": "Text",
    "index_reference": "21008017",
    "language": "zht",
    "content": "<p><strong>人無法理解的事是什麼？</strong></p><p>人無法理解日光之下所做的工。</p>",
    "associations": {
      "passage": [
        {
          "start_ref": "21008017",
          "start_ref_usfm": "ECC 8:17",
          "end_ref": "21008017",
          "end_ref_usfm": "ECC 8:17"
        }
      ],
      "resource": []
    }
  },
  {
    "content_id": 613087,
    "reference_id": 123146,
    "version": "1.0.0",
    "title": "傳道書 9:1",
    "media_type": "Text",
    "index_reference": "21009001",
    "language": "zht",
    "content": "<p><strong>誰在神的手中？</strong></p><p>義人和智慧人都在神的手中。</p>",
    "associations": {
      "passage": [
        {
          "start_ref": "21009001",
          "start_ref_usfm": "ECC 9:1",
          "end_ref": "21009001",
          "end_ref_usfm": "ECC 9:1"
        }
      ],
      "resource": []
    }
  },
  {
    "content_id": 613088,
    "reference_id": 123147,
    "version": "1.0.0",
    "title": "傳道書 9:2",
    "media_type": "Text",
    "index_reference": "21009002",
    "language": "zht",
    "content": "<p><strong>什麼對眾人都是一樣的？</strong></p><p>眾人都遭遇一樣的命運。</p>",
    "associations": {
      "passage": [
        {
          "start_ref": "21009002",
          "start_ref_usfm": "ECC 9:2",
          "end_ref": "21009002",
          "end_ref_usfm": "ECC 9:2"
        }
      ],
      "resource": []
    }
  },
  {
    "content_id": 613089,
    "reference_id": 123148,
    "version": "1.0.0",
    "title": "傳道書 9:3",
    "media_type": "Text",
    "index_reference": "21009003",
    "language": "zht",
    "content": "<p><strong>世人的心充滿了什麼呢？</strong></p><p>世人的心充滿了惡。</p>",
    "associations": {
      "passage": [
        {
          "start_ref": "21009003",
          "start_ref_usfm": "ECC 9:3",
          "end_ref": "21009003",
          "end_ref_usfm": "ECC 9:3"
        }
      ],
      "resource": []
    }
  },
  {
    "content_id": 613090,
    "reference_id": 123149,
    "version": "1.0.0",
    "title": "傳道書 9:5",
    "media_type": "Text",
    "index_reference": "21009005",
    "language": "zht",
    "content": "<p><strong>死了的人為什麼不再得賞賜？</strong></p><p>死了的人不再得賞賜，因為他們的名無人記念。</p>",
    "associations": {
      "passage": [
        {
          "start_ref": "21009005",
          "start_ref_usfm": "ECC 9:5",
          "end_ref": "21009005",
          "end_ref_usfm": "ECC 9:5"
        }
      ],
      "resource": []
    }
  },
  {
    "content_id": 613091,
    "reference_id": 123150,
    "version": "1.0.0",
    "title": "傳道書 9:6",
    "media_type": "Text",
    "index_reference": "21009006",
    "language": "zht",
    "content": "<p><strong>什麼早都消滅了？</strong></p><p>死了的人的愛、恨和嫉妒，早都消滅了。</p>",
    "associations": {
      "passage": [
        {
          "start_ref": "21009006",
          "start_ref_usfm": "ECC 9:6",
          "end_ref": "21009006",
          "end_ref_usfm": "ECC 9:6"
        }
      ],
      "resource": []
    }
  },
  {
    "content_id": 613092,
    "reference_id": 123151,
    "version": "1.0.0",
    "title": "傳道書 9:10",
    "media_type": "Text",
    "index_reference": "21009010",
    "language": "zht",
    "content": "<p><strong>凡人手所當做的事，要怎樣做？</strong></p><p>凡人手所當做的事，要盡力去做。</p>",
    "associations": {
      "passage": [
        {
          "start_ref": "21009010",
          "start_ref_usfm": "ECC 9:10",
          "end_ref": "21009010",
          "end_ref_usfm": "ECC 9:10"
        }
      ],
      "resource": []
    }
  },
  {
    "content_id": 613093,
    "reference_id": 123152,
    "version": "1.0.0",
    "title": "傳道書 9:12",
    "media_type": "Text",
    "index_reference": "21009012",
    "language": "zht",
    "content": "<p><strong>世人陷在什麼之中？</strong></p><p>世人陷在忽然臨到的禍患之中。</p>",
    "associations": {
      "passage": [
        {
          "start_ref": "21009012",
          "start_ref_usfm": "ECC 9:12",
          "end_ref": "21009012",
          "end_ref_usfm": "ECC 9:12"
        }
      ],
      "resource": []
    }
  },
  {
    "content_id": 613094,
    "reference_id": 123153,
    "version": "1.0.0",
    "title": "傳道書 9:15",
    "media_type": "Text",
    "index_reference": "21009015",
    "language": "zht",
    "content": "<p><strong>那貧窮的智慧人，他用智慧救了那城，然後他怎麼了？</strong></p><p>那貧窮的智慧人，他用智慧救了那城，然後卻沒有人記念那窮人。</p>",
    "associations": {
      "passage": [
        {
          "start_ref": "21009015",
          "start_ref_usfm": "ECC 9:15",
          "end_ref": "21009015",
          "end_ref_usfm": "ECC 9:15"
        }
      ],
      "resource": []
    }
  },
  {
    "content_id": 613095,
    "reference_id": 123154,
    "version": "1.0.0",
    "title": "傳道書 9:18",
    "media_type": "Text",
    "index_reference": "21009018",
    "language": "zht",
    "content": "<p><strong>什麼勝過打仗的兵器？</strong></p><p>智慧勝過打仗的兵器。</p>",
    "associations": {
      "passage": [
        {
          "start_ref": "21009018",
          "start_ref_usfm": "ECC 9:18",
          "end_ref": "21009018",
          "end_ref_usfm": "ECC 9:18"
        }
      ],
      "resource": []
    }
  },
  {
    "content_id": 613096,
    "reference_id": 123155,
    "version": "1.0.0",
    "title": "傳道書 10:3",
    "media_type": "Text",
    "index_reference": "21010003",
    "language": "zht",
    "content": "<p><strong>什麼會顯出一個人是愚昧人？</strong></p><p>當一個人的思想是無知時，他向眾人顯出他是愚昧人。</p>",
    "associations": {
      "passage": [
        {
          "start_ref": "21010003",
          "start_ref_usfm": "ECC 10:3",
          "end_ref": "21010003",
          "end_ref_usfm": "ECC 10:3"
        }
      ],
      "resource": []
    }
  },
  {
    "content_id": 613097,
    "reference_id": 123156,
    "version": "1.0.0",
    "title": "傳道書 10:7",
    "media_type": "Text",
    "index_reference": "21010007",
    "language": "zht",
    "content": "<p><strong>傳道者見僕人在做什麼？</strong></p><p>傳道者見僕人在騎馬。</p>",
    "associations": {
      "passage": [
        {
          "start_ref": "21010007",
          "start_ref_usfm": "ECC 10:7",
          "end_ref": "21010007",
          "end_ref_usfm": "ECC 10:7"
        }
      ],
      "resource": []
    }
  },
  {
    "content_id": 613098,
    "reference_id": 123157,
    "version": "1.0.0",
    "title": "傳道書 10:8",
    "media_type": "Text",
    "index_reference": "21010008",
    "language": "zht",
    "content": "<p><strong>拆牆垣的人，會發生什麼事？</strong></p><p>拆牆垣的人，必為蛇所咬。</p>",
    "associations": {
      "passage": [
        {
          "start_ref": "21010008",
          "start_ref_usfm": "ECC 10:8",
          "end_ref": "21010008",
          "end_ref_usfm": "ECC 10:8"
        }
      ],
      "resource": []
    }
  },
  {
    "content_id": 613099,
    "reference_id": 123158,
    "version": "1.0.0",
    "title": "傳道書 10:10",
    "media_type": "Text",
    "index_reference": "21010010",
    "language": "zht",
    "content": "<p><strong>鐵器鈍了，人若不將刃磨快，就會怎樣？</strong></p><p>鐵器鈍了，人若不將刃磨快，就必多費氣力。</p>",
    "associations": {
      "passage": [
        {
          "start_ref": "21010010",
          "start_ref_usfm": "ECC 10:10",
          "end_ref": "21010010",
          "end_ref_usfm": "ECC 10:10"
        }
      ],
      "resource": []
    }
  },
  {
    "content_id": 613100,
    "reference_id": 123159,
    "version": "1.0.0",
    "title": "傳道書 10:13",
    "media_type": "Text",
    "index_reference": "21010013",
    "language": "zht",
    "content": "<p><strong>愚昧人口中言語的末尾是什麼呢？</strong></p><p>愚昧人口中言語的末尾是奸惡的狂妄。</p>",
    "associations": {
      "passage": [
        {
          "start_ref": "21010013",
          "start_ref_usfm": "ECC 10:13",
          "end_ref": "21010013",
          "end_ref_usfm": "ECC 10:13"
        }
      ],
      "resource": []
    }
  },
  {
    "content_id": 613101,
    "reference_id": 123160,
    "version": "1.0.0",
    "title": "傳道書 10:16",
    "media_type": "Text",
    "index_reference": "21010016",
    "language": "zht",
    "content": "<p><strong>邦國什麼時候就有禍了？</strong></p><p>邦國的王若是孩童，群臣早晨就開始宴樂， 這國就有禍了！</p>",
    "associations": {
      "passage": [
        {
          "start_ref": "21010016",
          "start_ref_usfm": "ECC 10:16",
          "end_ref": "21010016",
          "end_ref_usfm": "ECC 10:16"
        }
      ],
      "resource": []
    }
  },
  {
    "content_id": 613102,
    "reference_id": 123161,
    "version": "1.0.0",
    "title": "傳道書 10:18",
    "media_type": "Text",
    "index_reference": "21010018",
    "language": "zht",
    "content": "<p><strong>為什麼房屋滴漏呢？</strong></p><p>因人手懶，房屋滴漏。</p>",
    "associations": {
      "passage": [
        {
          "start_ref": "21010018",
          "start_ref_usfm": "ECC 10:18",
          "end_ref": "21010018",
          "end_ref_usfm": "ECC 10:18"
        }
      ],
      "resource": []
    }
  },
  {
    "content_id": 613103,
    "reference_id": 123162,
    "version": "1.0.0",
    "title": "傳道書 10:20",
    "media_type": "Text",
    "index_reference": "21010020",
    "language": "zht",
    "content": "<p><strong>為什麼人不可咒詛君王？</strong></p><p>人不可咒詛君王，因為空中的鳥必傳揚這聲音。</p>",
    "associations": {
      "passage": [
        {
          "start_ref": "21010020",
          "start_ref_usfm": "ECC 10:20",
          "end_ref": "21010020",
          "end_ref_usfm": "ECC 10:20"
        }
      ],
      "resource": []
    }
  },
  {
    "content_id": 613104,
    "reference_id": 123163,
    "version": "1.0.0",
    "title": "傳道書 11:2",
    "media_type": "Text",
    "index_reference": "21011002",
    "language": "zht",
    "content": "<p><strong>為什麼人當將他的糧食分給七人，或分給八人？</strong></p><p>人當將他的糧食分給七人，或分給八人，因為他們不知道將來有甚麼災禍臨到地上。</p>",
    "associations": {
      "passage": [
        {
          "start_ref": "21011002",
          "start_ref_usfm": "ECC 11:2",
          "end_ref": "21011002",
          "end_ref_usfm": "ECC 11:2"
        }
      ],
      "resource": []
    }
  },
  {
    "content_id": 613105,
    "reference_id": 123164,
    "version": "1.0.0",
    "title": "傳道書 11:5",
    "media_type": "Text",
    "index_reference": "21011005",
    "language": "zht",
    "content": "<p><strong>人不得知道什麼？</strong></p><p>行萬事之神的作為，人不得知道。</p>",
    "associations": {
      "passage": [
        {
          "start_ref": "21011005",
          "start_ref_usfm": "ECC 11:5",
          "end_ref": "21011005",
          "end_ref_usfm": "ECC 11:5"
        }
      ],
      "resource": []
    }
  },
  {
    "content_id": 613106,
    "reference_id": 123165,
    "version": "1.0.0",
    "title": "傳道書 11:6",
    "media_type": "Text",
    "index_reference": "21011006",
    "language": "zht",
    "content": "<p><strong>人當撒種的時間是多長？</strong></p><p>從早晨到晚上，人都當撒種。</p>",
    "associations": {
      "passage": [
        {
          "start_ref": "21011006",
          "start_ref_usfm": "ECC 11:6",
          "end_ref": "21011006",
          "end_ref_usfm": "ECC 11:6"
        }
      ],
      "resource": []
    }
  },
  {
    "content_id": 613107,
    "reference_id": 123166,
    "version": "1.0.0",
    "title": "傳道書 11:10",
    "media_type": "Text",
    "index_reference": "21011010",
    "language": "zht",
    "content": "<p><strong>人當從心中除掉什麼？</strong></p><p>人當從心中除掉愁煩。</p>",
    "associations": {
      "passage": [
        {
          "start_ref": "21011010",
          "start_ref_usfm": "ECC 11:10",
          "end_ref": "21011010",
          "end_ref_usfm": "ECC 11:10"
        }
      ],
      "resource": []
    }
  },
  {
    "content_id": 613108,
    "reference_id": 123167,
    "version": "1.0.0",
    "title": "傳道書 12:1",
    "media_type": "Text",
    "index_reference": "21012001",
    "language": "zht",
    "content": "<p><strong>人當何時記念他們的造物主？</strong></p><p>人當趁著年幼的日子記念他們的造物主。</p>",
    "associations": {
      "passage": [
        {
          "start_ref": "21012001",
          "start_ref_usfm": "ECC 12:1",
          "end_ref": "21012001",
          "end_ref_usfm": "ECC 12:1"
        }
      ],
      "resource": []
    }
  },
  {
    "content_id": 613109,
    "reference_id": 123168,
    "version": "1.0.0",
    "title": "傳道書 12:3",
    "media_type": "Text",
    "index_reference": "21012003",
    "language": "zht",
    "content": "<p><strong>為什麼推磨的婦人會止息工作？</strong></p><p>因推磨的婦人稀少，就止息了工作。</p>",
    "associations": {
      "passage": [
        {
          "start_ref": "21012003",
          "start_ref_usfm": "ECC 12:3",
          "end_ref": "21012003",
          "end_ref_usfm": "ECC 12:3"
        }
      ],
      "resource": []
    }
  },
  {
    "content_id": 613110,
    "reference_id": 123169,
    "version": "1.0.0",
    "title": "傳道書 12:4",
    "media_type": "Text",
    "index_reference": "21012004",
    "language": "zht",
    "content": "<p><strong>人會被什麼驚嚇？</strong></p><p>人會被雀鳥的叫聲驚嚇。</p>",
    "associations": {
      "passage": [
        {
          "start_ref": "21012004",
          "start_ref_usfm": "ECC 12:4",
          "end_ref": "21012004",
          "end_ref_usfm": "ECC 12:4"
        }
      ],
      "resource": []
    }
  },
  {
    "content_id": 613111,
    "reference_id": 123170,
    "version": "1.0.0",
    "title": "傳道書 12:7",
    "media_type": "Text",
    "index_reference": "21012007",
    "language": "zht",
    "content": "<p><strong>塵土將歸於何處呢？</strong></p><p>塵土將歸於地。</p>",
    "associations": {
      "passage": [
        {
          "start_ref": "21012007",
          "start_ref_usfm": "ECC 12:7",
          "end_ref": "21012007",
          "end_ref_usfm": "ECC 12:7"
        }
      ],
      "resource": []
    }
  },
  {
    "content_id": 613112,
    "reference_id": 123171,
    "version": "1.0.0",
    "title": "傳道書 12:9",
    "media_type": "Text",
    "index_reference": "21012009",
    "language": "zht",
    "content": "<p><strong>傳道者將什麼教訓眾人？</strong></p><p>傳道者將知識教訓眾人。</p>",
    "associations": {
      "passage": [
        {
          "start_ref": "21012009",
          "start_ref_usfm": "ECC 12:9",
          "end_ref": "21012009",
          "end_ref_usfm": "ECC 12:9"
        }
      ],
      "resource": []
    }
  },
  {
    "content_id": 613113,
    "reference_id": 123172,
    "version": "1.0.0",
    "title": "傳道書 12:11",
    "media_type": "Text",
    "index_reference": "21012011",
    "language": "zht",
    "content": "<p><strong>智慧人的言語好像什麼呢？</strong></p><p>智慧人的言語好像刺棍。</p>",
    "associations": {
      "passage": [
        {
          "start_ref": "21012011",
          "start_ref_usfm": "ECC 12:11",
          "end_ref": "21012011",
          "end_ref_usfm": "ECC 12:11"
        }
      ],
      "resource": []
    }
  },
  {
    "content_id": 613114,
    "reference_id": 123173,
    "version": "1.0.0",
    "title": "傳道書 12:12",
    "media_type": "Text",
    "index_reference": "21012012",
    "language": "zht",
    "content": "<p><strong>讀書多帶來什麼影響？</strong></p><p>讀書多，身體疲倦。</p>",
    "associations": {
      "passage": [
        {
          "start_ref": "21012012",
          "start_ref_usfm": "ECC 12:12",
          "end_ref": "21012012",
          "end_ref_usfm": "ECC 12:12"
        }
      ],
      "resource": []
    }
  },
  {
    "content_id": 613115,
    "reference_id": 123174,
    "version": "1.0.0",
    "title": "傳道書 12:13",
    "media_type": "Text",
    "index_reference": "21012013",
    "language": "zht",
    "content": "<p><strong>事情的總意是什麼？</strong></p><p>事情的總意就是，人必須敬畏神，謹守祂的誡命。</p>",
    "associations": {
      "passage": [
        {
          "start_ref": "21012013",
          "start_ref_usfm": "ECC 12:13",
          "end_ref": "21012013",
          "end_ref_usfm": "ECC 12:13"
        }
      ],
      "resource": []
    }
  }
]